Workbook

Sheet Portada
B2: Bolivia: ¿otro programa de estabilización es posible?
B3: Simulación contrafactual del Acuerdo SAF/EFF del FMI (36 meses, 2026–2029) · Maestría GPP · Macroeconomía para el Desarrollo
B5: Pregunta central | C5: ¿Se puede alcanzar la estabilidad que persigue el FMI con otra combinación de políticas fiscal, monetaria, cambiaria y tributaria, con menor costo social o recuperación productiva más rápida?
B6: Fuente principal | C6: FMI, Bolivia: Solicitud de un Acuerdo Ampliado en virtud del SAF (Informe del personal, 22-sep-2026; aprobación del Directorio 2-oct-2026, PR26/317). Versión traducida automáticamente; cifras leídas de Tablas 1, 2a, 2b, 4a, 4b, 5, 6 y Tablas de texto 1–3.
B7: Metas de prueba | C7: Criterios cuantitativos e indicativos a dic-2026 según la consigna (saldo primario, RIN, crédito BCB, asistencia social, base monetaria).
B8: Cómo usarlo | C8: 1) Elija escenario, shock, año del shock y respuesta en el Dashboard (celdas amarillas). 2) Ajuste las palancas de cada escenario en 'Palancas' (texto azul). 3) Ajuste parámetros en 'Supuestos'. Todo se recalcula con fórmulas.
B9: Escenarios | C9: Base FMI · E1 Fiscal gradual · E2 Monetaria con crédito productivo · E3 Banda cambiaria · E4 Tributaria progresiva · E5 Protección social y subsidio gradual · E6 Programa alternativo integrado (combinación eficiente).
B10: Naturaleza del modelo | C10: Modelo semiestructural de desviaciones respecto de la senda FMI: cada escenario = proyección FMI + efecto de las palancas vía multiplicadores, traspasos y elasticidades documentados. No es econométrico; es una herramienta de coherencia contable y de canales de transmisión para la defensa oral.
B11: Convención de colores | C11: Texto azul = dato de entrada/palanca editable · Negro = fórmula · Verde = vínculo a otra hoja · Fondo amarillo = selector o supuesto clave.
B12: Advertencia | C12: Las proyecciones alternativas son ejercicios contrafactuales del equipo, no pronósticos oficiales. Los shocks son hipotéticos (consigna, misión 5).
B14: Hojas
B15: Dashboard | C15: Selectores, semáforo de metas, indicadores clave, comparación de escenarios y gráficos.
B16: Datos_FMI | C16: Senda base del programa 2024–2031 transcrita del informe, con fuente por fila.
B17: Metas | C17: Las cinco metas de prueba a dic-2026.
B18: Supuestos | C18: Parámetros del modelo (multiplicadores, traspasos, elasticidades) con justificación.
B19: Palancas | C19: Decisiones de política por escenario y año (entradas).
B20: Motor | C20: Cálculo por escenario: fiscal, financiamiento, crecimiento, inflación, deuda, reservas, crédito, empleo y distribución.
B21: Shocks | C21: Cisne negro boliviano: impacto de cada shock sobre el escenario elegido, con respuesta de política.
B22: Seleccionado | C22: Escenario elegido + shock, frente a la Base FMI (alimenta el Dashboard).
B23: Evaluacion | C23: Cumplimiento de metas y índice de eficiencia de todos los escenarios.
B24: Contrafactual | C24: Presupuesto contrafactual de la consigna: FMI vs alternativo con justificación.
B25: Matriz_Instrumentos | C25: Qué instrumento cambia, cómo funciona, quién gana/pierde, costo, financiamiento y riesgo.
B26: Diagnostico | C26: Auditoría del diagnóstico del FMI (misión 1).
... B28: Negociacion | C28: Condicionalidad alternativa: metas verificables, calendario y seguimiento (misión 6).

Sheet Dashboard
B2: Bolivia 2026–2029 · Programa FMI vs programa alternativo
B3: Simulación contrafactual con metas de prueba a dic-2026, shocks 'cisne negro' y evaluación de eficiencia. Cifras en Bs mn / US$ mn / % según fila.
B5: Escenario a evaluar | C5: E6 Alternativo integrado | G5: Descripción del escenario
B6: Shock (cisne negro) | C6: Ninguno | G6: =INDEX(Listas!$C$2:$C$8,MATCH(sel_scen,Listas!$B$2:$B$8,0)) -> Combinación eficiente: 2026 intacto para cumplir metas; desde 2027 inversión productiva + reforma tributaria progresiva/antievasión + recorte de gasto corriente y reestructuración de EP + crédito productivo neutral en base monetaria + flotación administrada con reglas + red social reforzada.
B7: Año del shock | C7: 2027
B8: ¿Activar respuesta de política? | C8: Sí
B10: Metas de prueba a dic-2026 · escenario seleccionado + shock | C10: Valor | D10: Meta | E10: Holgura | F10: Estado | H10: Indicador | J10: FMI 2026 | K10: FMI 2027 | L10: FMI 2028 | M10: FMI 2029 | N10: Alt. 2026 | O10: Alt. 2027 | P10: Alt. 2028 | Q10: Alt. 2029
B11: =Seleccionado!B25 -> Saldo primario (Bs mn) | C11: =Seleccionado!C25 -> -32751.77 | D11: =Seleccionado!D25 -> -33000 | E11: =Seleccionado!E25 -> 248.22952 | F11: =Seleccionado!F25 -> Cumple | H11: =Seleccionado!B7 -> Crecimiento PIB real (%) | J11: =Seleccionado!C7 -> -3 | K11: =Seleccionado!D7 -> -1.5 | L11: =Seleccionado!E7 -> 0.5 | M11: =Seleccionado!F7 -> 2.5 | N11: =Seleccionado!G7 -> -2.97175 | O11: =Seleccionado!H7 -> -0.808 | P11: =Seleccionado!I7 -> 1.059 | Q11: =Seleccionado!J7 -> 2.861
B12: =Seleccionado!B26 -> Variación RIN (US$ mn) | C12: =Seleccionado!C26 -> 2403.7065 | D12: =Seleccionado!D26 -> 2400 | E12: =Seleccionado!E26 -> 3.706515 | F12: =Seleccionado!F26 -> Cumple | H12: =Seleccionado!B8 -> Inflación promedio (%) | J12: =Seleccionado!C8 -> 12.7 | K12: =Seleccionado!D8 -> 15.8 | L12: =Seleccionado!E8 -> 8.2 | M12: =Seleccionado!F8 -> 7.3 | N12: =Seleccionado!G8 -> 12.710562 | O12: =Seleccionado!H8 -> 15.8265 | P12: =Seleccionado!I8 -> 8.31375 | Q12: =Seleccionado!J8 -> 7.32725
B13: =Seleccionado!B27 -> Crédito BCB al sector público (Bs mn) | C13: =Seleccionado!C27 -> 0 | D13: =Seleccionado!D27 -> 0 | E13: =Seleccionado!E27 -> 0 | F13: =Seleccionado!F27 -> Cumple | H13: =Seleccionado!B10 -> Saldo primario (% PIB) | J13: =Seleccionado!C10 -> -6.5 | K13: =Seleccionado!D10 -> -3 | L13: =Seleccionado!E10 -> -0.3 | M13: =Seleccionado!F10 -> 0.6 | N13: =Seleccionado!G10 -> -6.47685 | O13: =Seleccionado!H10 -> -2.8866 | P13: =Seleccionado!I10 -> 0.4518 | Q13: =Seleccionado!J10 -> 1.6622
B14: =Seleccionado!B28 -> Asistencia social (Bs mn) | C14: =Seleccionado!C28 -> 10890 | D14: =Seleccionado!D28 -> 9300 | E14: =Seleccionado!E28 -> 1590 | F14: =Seleccionado!F28 -> Cumple | H14: =Seleccionado!B13 -> Deuda SPNF (% PIB) | J14: =Seleccionado!C13 -> 100.47769 | K14: =Seleccionado!D13 -> 95.361223 | L14: =Seleccionado!E13 -> 93.185529 | M14: =Seleccionado!F13 -> 89.203374 | N14: =Seleccionado!G13 -> 100.41557 | O14: =Seleccionado!H13 -> 94.214638 | P14: =Seleccionado!I13 -> 90.314434 | Q14: =Seleccionado!J13 -> 84.846923
B15: =Seleccionado!B29 -> Base monetaria (Bs mn) | C15: =Seleccionado!C29 -> 133900 | D15: =Seleccionado!D29 -> 133900 | E15: =Seleccionado!E29 -> 0 | F15: =Seleccionado!F29 -> Cumple | H15: =Seleccionado!B14 -> RIN del programa (US$ mn) | J15: =Seleccionado!C14 -> -581 | K15: =Seleccionado!D14 -> 744 | L15: =Seleccionado!E14 -> 1304 | M15: =Seleccionado!F14 -> 1878 | N15: =Seleccionado!G14 -> -586.29349 | O15: =Seleccionado!H14 -> 703.74912 | P15: =Seleccionado!I14 -> 1302.8827 | Q15: =Seleccionado!J14 -> 1800.8561
B16: Metas cumplidas | C16: =COUNTIF(F11:F15,"Cumple")&" de 5" -> 5 de 5 | H16: =Seleccionado!B16 -> Crédito privado (variación %) | J16: =Seleccionado!C16 -> 4 | K16: =Seleccionado!D16 -> 7.3 | L16: =Seleccionado!E16 -> 7.3 | M16: =Seleccionado!F16 -> 9.5 | N16: =Seleccionado!G16 -> 4.25 | O16: =Seleccionado!H16 -> 10.55 | P16: =Seleccionado!I16 -> 10.3 | Q16: =Seleccionado!J16 -> 11.5
H17: =Seleccionado!B19 -> Asistencia social (Bs mn) | J17: =Seleccionado!C19 -> 10890 | K17: =Seleccionado!D19 -> 12722.578 | L17: =Seleccionado!E19 -> 8064.823 | M17: =Seleccionado!F19 -> 8813.142 | N17: =Seleccionado!G19 -> 10890 | O17: =Seleccionado!H19 -> 14168.326 | P17: =Seleccionado!I19 -> 9305.565 | Q17: =Seleccionado!J19 -> 9830.043
H18: =Seleccionado!B20 -> Δ Empleo vs FMI (miles) | J18: =Seleccionado!C20 -> 0 | K18: =Seleccionado!D20 -> 0 | L18: =Seleccionado!E20 -> 0 | M18: =Seleccionado!F20 -> 0 | N18: =Seleccionado!G20 -> 0.904 | O18: =Seleccionado!H20 -> 23.048 | P18: =Seleccionado!I20 -> 40.936 | Q18: =Seleccionado!J20 -> 52.488
H19: =Seleccionado!B21 -> Δ Pobreza vs FMI (pp) | J19: =Seleccionado!C21 -> 0 | K19: =Seleccionado!D21 -> 0 | L19: =Seleccionado!E21 -> 0 | M19: =Seleccionado!F21 -> 0 | N19: =Seleccionado!G21 -> -0.018190625 | O19: =Seleccionado!H21 -> -1.0602 | P19: =Seleccionado!I21 -> -1.2784125 | Q19: =Seleccionado!J21 -> -1.4440875
B22: Comparación de escenarios (sin shock) | C22: Base FMI | D22: E1 Fiscal gradual | E22: E2 Monetaria-crédito | F22: E3 Banda cambiaria | G22: E4 Tributaria progresiva | H22: E5 Protección social | I22: E6 Alternativo integrado
B23: Metas 2026 cumplidas (de 5) | C23: =Evaluacion!C16 -> 5 | D23: =Evaluacion!D16 -> 4 | E23: =Evaluacion!E16 -> 5 | F23: =Evaluacion!F16 -> 4 | G23: =Evaluacion!G16 -> 5 | H23: =Evaluacion!H16 -> 5 | I23: =Evaluacion!I16 -> 5
B24: Meta saldo primario | C24: =Evaluacion!C11 -> Cumple | D24: =Evaluacion!D11 -> No cumple | E24: =Evaluacion!E11 -> Cumple | F24: =Evaluacion!F11 -> Cumple | G24: =Evaluacion!G11 -> Cumple | H24: =Evaluacion!H11 -> Cumple | I24: =Evaluacion!I11 -> Cumple
B25: Meta RIN | C25: =Evaluacion!C12 -> Cumple | D25: =Evaluacion!D12 -> Cumple | E25: =Evaluacion!E12 -> Cumple | F25: =Evaluacion!F12 -> No cumple | G25: =Evaluacion!G12 -> Cumple | H25: =Evaluacion!H12 -> Cumple | I25: =Evaluacion!I12 -> Cumple
B26: Meta crédito BCB | C26: =Evaluacion!C13 -> Cumple | D26: =Evaluacion!D13 -> Cumple | E26: =Evaluacion!E13 -> Cumple | F26: =Evaluacion!F13 -> Cumple | G26: =Evaluacion!G13 -> Cumple | H26: =Evaluacion!H13 -> Cumple | I26: =Evaluacion!I13 -> Cumple
B27: Meta asistencia social | C27: =Evaluacion!C14 -> Cumple | D27: =Evaluacion!D14 -> Cumple | E27: =Evaluacion!E14 -> Cumple | F27: =Evaluacion!F14 -> Cumple | G27: =Evaluacion!G14 -> Cumple | H27: =Evaluacion!H14 -> Cumple | I27: =Evaluacion!I14 -> Cumple
B28: Meta base monetaria | C28: =Evaluacion!C15 -> Cumple | D28: =Evaluacion!D15 -> Cumple | E28: =Evaluacion!E15 -> Cumple | F28: =Evaluacion!F15 -> Cumple | G28: =Evaluacion!G15 -> Cumple | H28: =Evaluacion!H15 -> Cumple | I28: =Evaluacion!I15 -> Cumple
B29: Crecimiento acumulado 2026–29 (%) | C29: =Evaluacion!C18 -> -1.5767069 | D29: =Evaluacion!D18 -> 0.17629456 | E29: =Evaluacion!E18 -> -0.065671377 | F29: =Evaluacion!F18 -> -1.8013202 | G29: =Evaluacion!G18 -> -2.2080605 | H29: =Evaluacion!H18 -> -1.3167587 | I29: =Evaluacion!I18 -> 0.046196877
B30: Inflación promedio 2026–29 (%) | C30: =Evaluacion!C19 -> 11 | D30: =Evaluacion!D19 -> 11.110938 | E30: =Evaluacion!E19 -> 11.676875 | F30: =Evaluacion!F19 -> 10.329555 | G30: =Evaluacion!G19 -> 11.041781 | H30: =Evaluacion!H19 -> 11.016394 | I30: =Evaluacion!I19 -> 11.044516
B31: Deuda 2029 (% PIB) | C31: =Evaluacion!C21 -> 89.203374 | D31: =Evaluacion!D21 -> 89.229857 | E31: =Evaluacion!E21 -> 85.830045 | F31: =Evaluacion!F21 -> 88.799442 | G31: =Evaluacion!G21 -> 86.134624 | H31: =Evaluacion!H21 -> 89.923874 | I31: =Evaluacion!I21 -> 84.846923
B32: RIN 2029 (US$ mn) | C32: =Evaluacion!C22 -> 1878 | D32: =Evaluacion!D22 -> 2727.2943 | E32: =Evaluacion!E22 -> 1397.2205 | F32: =Evaluacion!F22 -> 771.74304 | G32: =Evaluacion!G22 -> 2007.4171 | H32: =Evaluacion!H22 -> 1980.4677 | I32: =Evaluacion!I22 -> 1800.8561
B33: Δ Pobreza 2029 (pp) | C33: =Evaluacion!C27 -> 0 | D33: =Evaluacion!D27 -> -1.2221563 | E33: =Evaluacion!E27 -> -0.99825 | F33: =Evaluacion!F27 -> 0.10535516 | G33: =Evaluacion!G27 -> 0.46481875 | H33: =Evaluacion!H27 -> -0.52869348 | I33: =Evaluacion!I27 -> -1.4440875
B34: Δ Empleo 2029 (miles) | C34: =Evaluacion!C26 -> 0 | D34: =Evaluacion!D26 -> 56.8 | E34: =Evaluacion!E26 -> 48.96 | F34: =Evaluacion!F26 -> -7.2676645 | G34: =Evaluacion!G26 -> -20.72 | H34: =Evaluacion!H26 -> 8.3937691 | I34: =Evaluacion!I26 -> 52.488
B35: Crédito BCB 2026–29 (Bs mn) | C35: =Evaluacion!C17 -> 0 | D35: =Evaluacion!D17 -> 0 | E35: =Evaluacion!E17 -> 0 | F35: =Evaluacion!F17 -> 0 | G35: =Evaluacion!G17 -> 0 | H35: =Evaluacion!H17 -> 0 | I35: =Evaluacion!I17 -> 0
B36: Índice de eficiencia (0–100) | C36: =Evaluacion!C38 -> 49.388775 | D36: =Evaluacion!D38 -> 52.18859 | E36: =Evaluacion!E38 -> 70.422955 | F36: =Evaluacion!F38 -> 24.484664 | G36: =Evaluacion!G38 -> 49.584885 | H36: =Evaluacion!H38 -> 53.092957 | I36: =Evaluacion!I38 -> 85.933332
B37: Ranking | C37: =Evaluacion!C39 -> 6 | D37: =Evaluacion!D39 -> 4 | E37: =Evaluacion!E39 -> 2 | F37: =Evaluacion!F39 -> 7 | G37: =Evaluacion!G39 -> 5 | H37: =Evaluacion!H39 -> 3 | I37: =Evaluacion!I39 -> 1
C38: Base FMI | D38: E1 Fiscal gradual | E38: E2 Monetaria-crédito | F38: E3 Banda cambiaria | G38: E4 Tributaria progresiva | H38: E5 Protección social | I38: E6 Alternativo integrado
B39: Saldo primario 2026 (Bs mn) | C39: =Evaluacion!C6 -> -32869 | D39: =Evaluacion!D6 -> -33413.37 | E39: =Evaluacion!E6 -> -32838.617 | F39: =Evaluacion!F6 -> -32884.192 | G39: =Evaluacion!G6 -> -32695.308 | H39: =Evaluacion!H6 -> -32858.872 | I39: =Evaluacion!I6 -> -32751.77
B40: Meta saldo primario 2026 | C40: =meta_pb -> -33000 | D40: =meta_pb -> -33000 | E40: =meta_pb -> -33000 | F40: =meta_pb -> -33000 | G40: =meta_pb -> -33000 | H40: =meta_pb -> -33000 | I40: =meta_pb -> -33000
B41: Variación RIN 2026 (US$ mn) | C41: =Evaluacion!C7 -> 2409 | D41: =Evaluacion!D7 -> 2492.6042 | E41: =Evaluacion!E7 -> 2403.3786 | F41: =Evaluacion!F7 -> 2261.8107 | G41: =Evaluacion!G7 -> 2409.6558 | H41: =Evaluacion!H7 -> 2407.1262 | I41: =Evaluacion!I7 -> 2403.7065
B42: Meta RIN 2026 | C42: =meta_nir -> 2400 | D42: =meta_nir -> 2400 | E42: =meta_nir -> 2400 | F42: =meta_nir -> 2400 | G42: =meta_nir -> 2400 | H42: =meta_nir -> 2400 | I42: =meta_nir -> 2400
B44: Años (categorías de gráficos) | C44: 2026 | D44: 2027 | E44: 2028 | F44: 2029
B46: Gráficos: escenario seleccionado (+shock) vs Base FMI
B77: Gráficos: comparación de los 7 escenarios (sin shock)

Sheet Datos_FMI
B2: Senda base del programa respaldado por el FMI (2024–2031)
B3: Est. 2024–2025; proyecciones del personal técnico 2026–2031. Fuente: Informe del personal FMI, sep-2026 (traducción automática).
B5: Indicador | C5: Unidad | D5: 2024 | E5: 2025 | F5: 2026 | G5: 2027 | H5: 2028 | I5: 2029 | J5: 2030 | K5: 2031 | L5: Fuente (informe FMI)
B6: PIB real (variación) | C6: % | D6: -1.1 | E6: -1.6 | F6: -3 | G6: -1.5 | H6: 0.5 | I6: 2.5 | J6: 2.9 | K6: 2.7 | L6: Tabla 1, p.41
B7: Inflación IPC (promedio del período) | C7: % | D7: 5.1 | E7: 19.5 | F7: 12.7 | G7: 15.8 | H7: 8.2 | I7: 7.3 | J7: 5.8 | K7: 5 | L7: Tabla 1, p.41
B8: Inflación IPC (fin de período) | C8: % | D8: 10 | E8: 20.4 | F8: 14.2 | G8: 10.7 | H8: 8.7 | I8: 6.2 | J8: 5.5 | K8: 5 | L8: Tabla 1, p.41
B9: PIB nominal | C9: Bs mn | D9: 379230 | E9: 447553 | F9: 506391 | G9: 578299 | H9: 620371 | I9: 677934 | J9: 733289 | K9: 786849 | L9: Tabla 2a, p.42
B10: Ingresos y donaciones SPNF | C10: % PIB | D10: 23 | E10: 16.8 | F10: 16.9 | G10: 17.3 | H10: 19.1 | I10: 20 | J10: 20.8 | K10: 20.9 | L10: Tabla 2b, p.43
B11: Gasto total SPNF | C11: % PIB | D11: 31.7 | E11: 28.2 | F11: 26.1 | G11: 24 | H11: 23 | I11: 23.2 | J11: 23.2 | K11: 23.1 | L11: Tabla 2b, p.43
B12: Inversión pública (adq. neta activos no financieros) | C12: % PIB | D12: 4.8 | E12: 3.5 | F12: 2.5 | G12: 2.7 | H12: 3.1 | I12: 3.3 | J12: 3.4 | K12: 3.6 | L12: Tabla 2b, p.43
B13: Prestaciones sociales (asistencia social, def. MTE) | C13: % PIB | D13: 1.6 | E13: 1.2 | F13: 2.2 | G13: 2.2 | H13: 1.3 | I13: 1.3 | J13: 1.3 | K13: 1.3 | L13: Tabla 2b, p.43
B14: Prestaciones sociales | C14: Bs mn | D14: 6069 | E14: 5525 | F14: 10890 | G14: =G13/100*G9 -> 12722.578 | H14: =H13/100*H9 -> 8064.823 | I14: =I13/100*I9 -> 8813.142 | J14: =J13/100*J9 -> 9532.757 | K14: =K13/100*K9 -> 10229.037 | L14: Tabla 2a, p.42
B15: Subsidios energéticos a empresas estatales | C15: % PIB | D15: 3.5 | E15: 3.3 | F15: 2.9 | G15: 0 | H15: 0 | I15: 0 | J15: 0 | K15: 0 | L15: Tabla 1 / Tabla 2b
B16: Intereses | C16: % PIB | D16: 2.6 | E16: 2.5 | F16: 2.7 | G16: 3.7 | H16: 3.7 | I16: 3.8 | J16: 3.7 | K16: 3.6 | L16: Tabla 2b, p.43
B17: Saldo primario SPNF | C17: % PIB | D17: -6.1 | E17: -8.8 | F17: -6.5 | G17: -3 | H17: -0.3 | I17: 0.6 | J17: 1.3 | K17: 1.4 | L17: Tabla 1 / 2b
B18: Saldo primario SPNF | C18: Bs mn | D18: -22971 | E18: -39587 | F18: -32869 | G18: -17466 | H18: =H17/100*H9 -> -1861.113 | I18: =I17/100*I9 -> 4067.604 | J18: =J17/100*J9 -> 9532.757 | K18: =K17/100*K9 -> 11015.886 | L18: Tabla 2a, p.42 (2028+ = %×PIB)
B19: Saldo global SPNF | C19: % PIB | D19: -8.7 | E19: -11.4 | F19: -9.2 | G19: -6.7 | H19: -4 | I19: -3.2 | J19: -2.4 | K19: -2.2 | L19: Tabla 1 / 2b
B20: Deuda bruta total SPNF | C20: % PIB | D20: 83.2 | E20: 83.3 | F20: 100.5 | G20: 95.4 | H20: 93.2 | I20: 89.2 | J20: 85.7 | K20: 82.7 | L20: Tabla 1 / 2b
B21: Deuda bruta total SPNF | C21: Bs mn | D21: 315590 | E21: 372887 | F21: 508810 | G21: 551473 | H21: 578096 | I21: 604740 | J21: 628114 | K21: 650725 | L21: Tabla 2a, p.42
B22: de la cual: deuda externa | C22: Bs mn | D22: 91550 | E22: 98284 | F22: 204596 | G22: 229658 | H22: 238910 | I22: 249488 | J22: 259994 | K22: 269237 | L22: Tabla 2a, p.42
B23: Cuenta corriente | C23: % PIB | D23: -2.4 | E23: -1.9 | F23: 1.6 | G23: 1 | H23: 0.4 | I23: -0.3 | J23: -1 | K23: -1.6 | L23: Tabla 1 / 4b
B24: Importaciones de bienes y servicios | C24: US$ mn | D24: n.d. | E24: n.d. | F24: 12492 | G24: 12389 | H24: 13222 | I24: 14040 | J24: 15116 | K24: 16394 | L24: Tabla 4a, p.45
B25: Importaciones de bienes y servicios | C25: % PIB | D25: 20.6 | E25: 17.6 | F25: 23.2 | G25: 28.2 | H25: 28.5 | I25: 28.1 | J25: 28.4 | K25: 29.1 | L25: Tabla 4b, p.46
B26: Importación de combustibles y lubricantes | C26: US$ mn | D26: n.d. | E26: n.d. | F26: 3845 | G26: 3215 | H26: 3107 | I26: 3126 | J26: 3152 | K26: 3175 | L26: Tabla 4a, p.45
B27: Reservas internacionales brutas (total BCB) | C27: US$ mn | D27: 1977 | E27: 3713 | F27: 5734 | G27: 7297 | H27: 8100 | I27: 8937 | J27: 9258 | K27: 9644 | L27: Tabla 1, p.41
B28: RIB del programa (netas de oro gravado) | C28: US$ mn | D28: 132 | E28: 627 | F28: 2458 | G28: 3982 | H28: 4690 | I28: 5527 | J28: 5847 | K28: 6234 | L28: Tabla 1, p.41
B29: RIB programa en % de la métrica ARA (flotante) | C29: % | D29: 2.7 | E29: 10.9 | F29: 53.4 | G29: 86.1 | H29: 100.1 | I29: 112.3 | J29: 114 | K29: 120.2 | L29: Tabla 1, p.41
B30: RIB programa en meses de importaciones | C30: meses | D30: 0.1 | E30: 0.6 | F30: 2.4 | G30: 3.6 | H30: 4 | I30: 4.4 | J30: 4.3 | K30: 4.3 | L30: Tabla 1, p.41
B31: Reservas internacionales netas del programa (stock) | C31: US$ mn | D31: n.d. | E31: -2990 | F31: -581 | G31: 744 | H31: 1304 | I31: 1878 | J31: 2199 | K31: 2676 | L31: Tabla 4a/4b, memo (p.45–46)
B32: Crédito al sector privado (variación) | C32: % | D32: 3.2 | E32: 3.1 | F32: 4 | G32: 7.3 | H32: 7.3 | I32: 9.5 | J32: 8.7 | K32: 8.4 | L32: Tabla 1 / Tabla 6
B33: Crédito bancario al sector privado | C33: % PIB | D33: 59.2 | E33: 51.7 | F33: 47.6 | G33: 44.7 | H33: 44.7 | I33: 44.8 | J33: 45 | K33: 45.5 | L33: Tabla 6, p.48
B34: Base monetaria (definición del programa) | C34: Bs mn | D34: 104819 | E34: 132269 | F34: 136564 | G34: 148333 | H34: 161304 | I34: 177013 | J34: 192144 | K34: 206603 | L34: Tabla 6, p.48
B35: Precio del petróleo (APSP) | C35: US$/barril | D35: 79.2 | E35: 67.7 | F35: 89.3 | G35: 78.7 | H35: 74.2 | I35: 71.5 | J35: 69.4 | K35: 67.6 | L35: Tabla de texto 2, p.14
B36: Financiamiento oficial neto IFI (excl. FMI) | C36: US$ mn | D36: n.d. | E36: n.d. | F36: 1500 | G36: 1800 | H36: 800 | I36: 0 | J36: n.d. | K36: n.d. | L36: Tabla de texto 3, p.27
B37: Desembolsos FMI (proyección) | C37: US$ mn | D37: n.d. | E37: n.d. | F37: 400 | G37: 700 | H37: 500 | I37: 300 | J37: n.d. | K37: n.d. | L37: Tabla de texto 3, p.27
B38: Nuevo financiamiento de mercado | C38: US$ mn | D38: n.d. | E38: n.d. | F38: 1000 | G38: 0 | H38: 0 | I38: 600 | J38: n.d. | K38: n.d. | L38: Tabla de texto 3, p.27
B40: Derivados (cálculo propio a partir del informe)
B41: PIB nominal en US$ (implícito = importaciones US$ ÷ % PIB) | C41: US$ mn | F41: =F24/(F25/100) -> 53844.828 | G41: =G24/(G25/100) -> 43932.624 | H41: =H24/(H25/100) -> 46392.982 | I41: =I24/(I25/100) -> 49964.413 | J41: =J24/(J25/100) -> 53225.352 | K41: =K24/(K25/100) -> 56336.77 | L41: Derivado: Tabla 4a ÷ Tabla 4b
B42: Tipo de cambio promedio implícito | C42: Bs/US$ | F42: =F9/F41 -> 9.4046359 | G42: =G9/G41 -> 13.163316 | H42: =H9/H41 -> 13.372087 | I42: =I9/I41 -> 13.568337 | J42: =J9/J41 -> 13.777062 | K42: =K9/K41 -> 13.966882 | L42: Derivado: PIB Bs ÷ PIB US$ (el informe cita Bs 12,8 de mercado en 2025)
B43: Variación de RIN del programa (meta: acumulada en el año) | C43: US$ mn | F43: =F31-E31 -> 2409 | G43: =G31-F31 -> 1325 | H43: =H31-G31 -> 560 | I43: =I31-H31 -> 574 | J43: =J31-I31 -> 321 | K43: =K31-J31 -> 477 | L43: 2026: +2.409 ≈ meta de +2.400 (consistencia)
B44: Indicadores sociales de referencia
B45: Tasa de pobreza (2024) | C45: % | D45: 37.7 | L45: Tabla 1, p.41
B46: Tasa de desempleo (2025) | C46: % | D46: 3 | L46: Tabla 1, p.41
B47: Población (2024) | C47: millones | D47: 12.3 | L47: Tabla 1, p.41

Sheet Metas
B2: Metas de prueba del programa a diciembre de 2026
B3: Fuente: consigna (tabla de criterios cuantitativos y metas indicativas del informe FMI). Valores de prueba, no resultados observados.
B5: Indicador del programa | C5: Tipo | D5: Meta | E5: Unidad | F5: Cómo se mide en el modelo
B6: Saldo primario acumulado del SPNF (piso) | C6: Criterio de desempeño | D6: -33000 | E6: Bs mn | F6: Saldo primario 2026 del escenario (Tabla 2a: base −32.869) + cambio discrecional y automático
B7: Variación acumulada de RIN del programa (piso) | C7: Criterio de desempeño | D7: 2400 | E7: US$ mn | F7: RIN programa 2026 − RIN 2025 (−2.990); base +2.409
B8: Nuevos créditos brutos del BCB al sector público (techo) | C8: Criterio continuo | D8: 0 | E8: Bs mn | F8: Brecha de financiamiento no cubierta por fuentes externas ni mercado interno
B9: Gasto acumulado en asistencia social (piso) | C9: Meta indicativa | D9: 9300 | E9: Bs mn | F9: Prestaciones sociales 2026 (Tabla 2a: 10.890) + asistencia adicional
B10: Base monetaria (techo) | C10: Meta indicativa | D10: 133900 | E10: Bs mn | F10: Supuesto: la senda base se calibra en la meta; + expansión del escenario + monetización
B12: Holgura de la senda base FMI frente a cada meta
B13: Saldo primario: −32.869 vs −33.000 → holgura de solo Bs 131 mn (0,03% del PIB). 2026 está prácticamente cerrado: cualquier gasto nuevo en el 4º trimestre rompe la meta.
B14: RIN: +2.409 vs +2.400 → holgura de US$ 9 mn. Cualquier intervención cambiaria en 2026 incumple el piso.

Sheet Supuestos
B2: Supuestos y parámetros del modelo (editables)
B3: Texto azul con fondo amarillo = parámetro. Rangos de literatura como referencia; calibración del equipo para fines docentes.
B5: Nombre | C5: Parámetro | D5: Valor | E5: Unidad | F5: Justificación / canal de transmisión
B6: Calendario
B7: ef26 | C7: Fracción de 2026 en que pueden operar medidas nuevas | D7: 0.25 | E7: fracción | F7: El informe es de sep-2026 y el Directorio aprobó el 2-oct-2026: solo queda el 4º trimestre. Se aplica a palancas en pp del PIB en 2026.
B8: Multiplicadores fiscales (efecto en pp del PIB real por 1 pp del PIB)
B9: m_inv | C9: Inversión pública productiva | D9: 0.7 | E9: x | F9: Ilzetzki-Mendoza-Végh (2013): multiplicadores de inversión mayores que los de consumo en países en desarrollo; contenido importado alto en Bolivia limita el valor.
B10: m_cur | C10: Gasto corriente (salarios, bienes y servicios, transferencias a EP) | D10: 0.4 | E10: x | F10: Economía con tipo de cambio más flexible y alta informalidad: multiplicador de consumo público moderado.
B11: m_sub | C11: Subsidio a combustibles | D11: 0.2 | E11: x | F11: Bajo: parte se filtra a contrabando e importaciones y beneficia a quintiles altos.
B12: m_soc | C12: Transferencias sociales focalizadas | D12: 0.6 | E12: x | F12: Alta propensión a consumir de hogares pobres (bonos Juancito Pinto, Juana Azurduy, PEPE).
B13: m_tev | C13: Recaudación por menor evasión / administración | D13: 0.1 | E13: x | F13: Recae sobre quien ya debía pagar; bajo efecto contractivo.
B14: m_tpr | C14: Recaudación por progresividad (renta personal, patrimonio, rentas financieras) | D14: 0.15 | E14: x | F14: Afecta a deciles altos con menor propensión marginal a consumir.
B15: m_tex | C15: Recaudación por revisión de exenciones | D15: 0.3 | E15: x | F15: Revertir exenciones de 2025–26 encarece importaciones e insumos de sectores beneficiados.
B16: Rendimiento real de la reforma tributaria (realización)
B17: r_tev | C17: Realización de medidas anti-evasión | D17: 0.7 | E17: fracción | F17: Facturación electrónica y fiscalización del SIN maduran con rezago; no se recauda el 100% del potencial.
B18: r_tpr | C18: Realización de medidas de progresividad | D18: 0.6 | E18: fracción | F18: Requiere ley; base estrecha, elusión y planificación fiscal.
B19: r_tex | C19: Realización de revisión de exenciones | D19: 0.85 | E19: fracción | F19: Medida administrativa/decreto de alta realización.
B20: Canales de crecimiento
B21: s_inv | C21: Efecto oferta de la inversión acumulada (pp de crecimiento por pp PIB invertido el año previo) | D21: 0.1 | E21: x | F21: Infraestructura productiva eleva el producto potencial con rezago (PIMA para filtrar proyectos).
B22: eps_cred | C22: Elasticidad del PIB al crecimiento del crédito privado | D22: 0.12 | E22: pp/pp | F22: Crédito/PIB ≈ 45% (Tabla 6): 1 pp más de crédito ≈ 0,45% del PIB de financiamiento, con impulso parcial a inversión.
B23: kappa | C23: Penalización de credibilidad por relajamiento fiscal (pp PIB por pp de déficit sobre la tolerancia) | D23: 0.3 | E23: x | F23: Mayor riesgo soberano (calificación CCC) eleva spreads y deprime inversión privada.
B24: tol | C24: Tolerancia de relajamiento sin costo de credibilidad | D24: 0.5 | E24: pp PIB | F24: Desvíos pequeños y anunciados con financiamiento identificado no alteran expectativas.
B25: nu_dep | C25: Efecto de la depreciación real sobre exportaciones netas | D25: 0.03 | E25: pp/pp | F25: Moderado: exportaciones dominadas por minerales y soya con precios internacionales.
B26: auto | C26: Estabilizador automático (mejora del saldo primario por pp de crecimiento) | D26: 0.2 | E26: pp/pp | F26: Gasto rígido en términos nominales e ingresos con elasticidad ≈1 al PIB.
B27: Canales de inflación
B28: phi_sub | C28: Traspaso de cambios en el subsidio a la inflación (pp por pp PIB de subsidio) | D28: 1.2 | E28: pp/pp | F28: Gasolina +86% y diésel +160% en dic-2025 (Recuadro 1) se reflejaron en transporte y alimentos.
B29: mu_bm | C29: Efecto de la expansión de la base monetaria sobre inflación | D29: 0.6 | E29: pp/pp | F29: Ancla nominal = base monetaria (párr. 22); traspaso parcial en el año.
B30: eta | C30: Presión de demanda (pp de inflación por pp de crecimiento) | D30: 0.25 | E30: pp/pp | F30: Brecha del producto negativa (3er año de recesión) limita la presión de demanda.
B31: psi | C31: Traspaso cambiario (pp de inflación por pp de depreciación) | D31: 0.35 | E31: pp/pp | F31: Economía muy abierta y dolarizada en precios de importados; rango regional 0,2–0,5.
B32: tax_pi | C32: Efecto precio del mayor cumplimiento del IVA | D32: 0.2 | E32: pp/pp | F32: Formalización del IVA traslada parte del impuesto a precios.
B33: bm_dep | C33: Depreciación adicional por pp de expansión de la base monetaria | D33: 0.5 | E33: pp/pp | F33: Exceso de liquidez en bolivianos presiona el mercado cambiario.
B34: Crédito y financiamiento
B35: bm_cred | C35: Crédito privado adicional por pp de base monetaria | D35: 0.5 | E35: pp/pp | F35: Más liquidez bancaria relaja tasas y topes.
B36: crowd | C36: Desplazamiento del crédito privado por financiamiento interno del Estado | D36: 0.5 | E36: fracción | F36: Gestora y bancos compran deuda pública en lugar de prestar al sector privado (con un año de rezago).
B37: r_int | C37: Tasa de interés efectiva sobre deuda adicional | D37: 0.065 | E37: fracción | F37: Mezcla de concesional multilateral (≈5%) y mercado interno; eurobono 2031 al 9,45%.
B38: cap_dom | C38: Capacidad del mercado interno para absorber deuda adicional | D38: 1 | E38: % PIB/año | F38: Gestora y bancos ya concentran deuda pública (párr. 26: riesgo del nexo soberano–pensiones).
B39: Sector externo
B40: imp_el | C40: Elasticidad de importaciones al PIB | D40: 1.5 | E40: x | F40: Alta dependencia de bienes de capital, insumos y combustibles importados.
B41: sub_leak | C41: Fracción del subsidio que se filtra en importaciones/contrabando | D41: 0.3 | E41: fracción | F41: Precio interno bajo vs países vecinos incentiva contrabando (DS 5676).
B42: bm_flight | C42: Pérdida de reservas por pp de expansión monetaria | D42: 60 | E42: US$ mn/pp | F42: Demanda de dólares por exceso de liquidez.
B43: monet_leak | C43: Fracción de la monetización que se convierte en demanda de divisas | D43: 0.5 | E43: fracción | F43: Experiencia 2024–25: financiamiento del BCB → brecha cambiaria y pérdida de reservas.
B44: Empleo y distribución
B45: emp_el | C45: Elasticidad empleo–producto | D45: 0.5 | E45: x | F45: Okun débil por informalidad: el ajuste se da en subempleo e ingresos.
B46: pea | C46: Población económicamente activa | D46: 6400 | E46: miles | F46: Aproximación INE (≈52% de 12,3 millones).
B47: pov_g | C47: Pobreza: pp por pp de PIB acumulado | D47: 0.7 | E47: pp/pp | F47: Elasticidad pobreza–crecimiento típica en América Latina (−0,5 a −1,0).
B48: pov_soc | C48: Pobreza: pp por pp PIB de transferencias focalizadas | D48: 2 | E48: pp/pp | F48: PEPE cubre 84% de los hogares pobres (Recuadro 1).
B49: pov_pi | C49: Pobreza: pp por pp de inflación | D49: 0.15 | E49: pp/pp | F49: Inflación de alimentos erosiona ingresos reales de los pobres.
B50: pov_sub | C50: Pobreza: pp por pp PIB de subsidio a combustibles | D50: 0.3 | E50: pp/pp | F50: Efecto pequeño: subsidio regresivo, pero abarata transporte y alimentos.
B51: gini_tpr | C51: Gini: puntos por pp PIB de recaudación progresiva | D51: 0.5 | E51: pts/pp | F51: Impuesto a la renta personal y patrimonio reduce desigualdad post-fiscal.
B52: gini_soc | C52: Gini: puntos por pp PIB de transferencias focalizadas | D52: 0.4 | E52: pts/pp | F52: Transferencias a quintiles bajos.
B53: Otros
B54: sub_full | C54: Subsidio que implica congelamiento total de precios de combustibles | D54: 1 | E54: pp PIB | F54: Usado en el shock petrolero: si el escenario mantiene ≥1 pp de subsidio, el Estado absorbe todo el alza.

Sheet Palancas
B2: Palancas de política por escenario (entradas editables)
B3: Desviaciones respecto de la senda FMI. Columna 2025 = 0 (referencia). En 2026 las palancas en pp del PIB se escalan por ef26 en el Motor.
B5: 0. Base FMI
B6: Programa del EFF tal como fue aprobado: consolidación fiscal anticipada (déficit primario −6,5% → +0,6% del PIB), eliminación del subsidio a combustibles a inicios de 2027, flotación con intervención solo ante condiciones desordenadas, metas de base monetaria y cero financiamiento del BCB.
B7: Palanca | C7: 2025 | D7: 2026 | E7: 2027 | F7: 2028 | G7: 2029 | H7: Unidad
B8: Δ Inversión pública productiva | C8: 0 | D8: 0 | E8: 0 | F8: 0 | G8: 0 | H8: pp PIB
B9: Δ Gasto corriente (salarios, bienes y servicios, transferencias a EP) | C9: 0 | D9: 0 | E9: 0 | F9: 0 | G9: 0 | H9: pp PIB
B10: Δ Subsidio a combustibles vs senda FMI | C10: 0 | D10: 0 | E10: 0 | F10: 0 | G10: 0 | H10: pp PIB
B11: Δ Asistencia social focalizada | C11: 0 | D11: 0 | E11: 0 | F11: 0 | G11: 0 | H11: pp PIB
B12: Δ Recaudación potencial: anti-evasión / administración | C12: 0 | D12: 0 | E12: 0 | F12: 0 | G12: 0 | H12: pp PIB
B13: Δ Recaudación potencial: progresividad (renta, patrimonio) | C13: 0 | D13: 0 | E13: 0 | F13: 0 | G13: 0 | H13: pp PIB
B14: Δ Recaudación potencial: revisión de exenciones | C14: 0 | D14: 0 | E14: 0 | F14: 0 | G14: 0 | H14: pp PIB
B15: Δ Crecimiento de la base monetaria vs programa | C15: 0 | D15: 0 | E15: 0 | F15: 0 | G15: 0 | H15: pp
B16: Δ Crédito productivo dirigido (encaje diferenciado, garantías) | C16: 0 | D16: 0 | E16: 0 | F16: 0 | G16: 0 | H16: pp crec. crédito
B17: Δ Depreciación vs flotación (− = suavizada por banda/intervención) | C17: 0 | D17: 0 | E17: 0 | F17: 0 | G17: 0 | H17: pp
B18: Δ Financiamiento externo concesional adicional | C18: 0 | D18: 0 | E18: 0 | F18: 0 | G18: 0 | H18: US$ mn
B19: Ventas netas de divisas para sostener banda/suavizar | C19: 0 | D19: 0 | E19: 0 | F19: 0 | G19: 0 | H19: US$ mn
B20: Régimen cambiario (0 = flotación FMI · 0,5 = flotación administrada con reglas · 1 = banda) | D20: 0
B23: 1. E1 Fiscal gradual
B24: Misma meta de deuda pero con senda más lenta: se protege y amplía la inversión pública productiva (filtrada por PIMA), financiada con préstamos de proyecto de CAF/BID y mercado interno. Pregunta: ¿reducir el déficit con otra velocidad protegiendo la inversión?
B25: Palanca | C25: 2025 | D25: 2026 | E25: 2027 | F25: 2028 | G25: 2029 | H25: Unidad
B26: Δ Inversión pública productiva | C26: 0 | D26: 0.5 | E26: 1 | F26: 0.8 | G26: 0.5 | H26: pp PIB
B27: Δ Gasto corriente (salarios, bienes y servicios, transferencias a EP) | C27: 0 | D27: 0 | E27: 0 | F27: 0 | G27: 0 | H27: pp PIB
B28: Δ Subsidio a combustibles vs senda FMI | C28: 0 | D28: 0 | E28: 0 | F28: 0 | G28: 0 | H28: pp PIB
B29: Δ Asistencia social focalizada | C29: 0 | D29: 0 | E29: 0 | F29: 0 | G29: 0 | H29: pp PIB
B30: Δ Recaudación potencial: anti-evasión / administración | C30: 0 | D30: 0 | E30: 0 | F30: 0 | G30: 0 | H30: pp PIB
B31: Δ Recaudación potencial: progresividad (renta, patrimonio) | C31: 0 | D31: 0 | E31: 0 | F31: 0 | G31: 0 | H31: pp PIB
B32: Δ Recaudación potencial: revisión de exenciones | C32: 0 | D32: 0 | E32: 0 | F32: 0 | G32: 0 | H32: pp PIB
B33: Δ Crecimiento de la base monetaria vs programa | C33: 0 | D33: 0 | E33: 0 | F33: 0 | G33: 0 | H33: pp
B34: Δ Crédito productivo dirigido (encaje diferenciado, garantías) | C34: 0 | D34: 0 | E34: 0 | F34: 0 | G34: 0 | H34: pp crec. crédito
B35: Δ Depreciación vs flotación (− = suavizada por banda/intervención) | C35: 0 | D35: 0 | E35: 0 | F35: 0 | G35: 0 | H35: pp
B36: Δ Financiamiento externo concesional adicional | C36: 0 | D36: 100 | E36: 500 | F36: 400 | G36: 200 | H36: US$ mn
B37: Ventas netas de divisas para sostener banda/suavizar | C37: 0 | D37: 0 | E37: 0 | F37: 0 | G37: 0 | H37: US$ mn
B38: Régimen cambiario (0 = flotación FMI · 0,5 = flotación administrada con reglas · 1 = banda) | D38: 0
B41: 2. E2 Monetaria-crédito
B42: Se mantiene la meta de base monetaria 2026; desde 2027 expansión moderada y crédito productivo dirigido mediante encaje diferenciado y fondos de garantía (sin topes de tasas). Pregunta: ¿estabilizar precios sin restringir en exceso el crédito?
B43: Palanca | C43: 2025 | D43: 2026 | E43: 2027 | F43: 2028 | G43: 2029 | H43: Unidad
B44: Δ Inversión pública productiva | C44: 0 | D44: 0 | E44: 0 | F44: 0 | G44: 0 | H44: pp PIB
B45: Δ Gasto corriente (salarios, bienes y servicios, transferencias a EP) | C45: 0 | D45: 0 | E45: 0 | F45: 0 | G45: 0 | H45: pp PIB
B46: Δ Subsidio a combustibles vs senda FMI | C46: 0 | D46: 0 | E46: 0 | F46: 0 | G46: 0 | H46: pp PIB
B47: Δ Asistencia social focalizada | C47: 0 | D47: 0 | E47: 0 | F47: 0 | G47: 0 | H47: pp PIB
B48: Δ Recaudación potencial: anti-evasión / administración | C48: 0 | D48: 0 | E48: 0 | F48: 0 | G48: 0 | H48: pp PIB
B49: Δ Recaudación potencial: progresividad (renta, patrimonio) | C49: 0 | D49: 0 | E49: 0 | F49: 0 | G49: 0 | H49: pp PIB
B50: Δ Recaudación potencial: revisión de exenciones | C50: 0 | D50: 0 | E50: 0 | F50: 0 | G50: 0 | H50: pp PIB
B51: Δ Crecimiento de la base monetaria vs programa | C51: 0 | D51: 0 | E51: 1.5 | F51: 1 | G51: 0.5 | H51: pp
B52: Δ Crédito productivo dirigido (encaje diferenciado, garantías) | C52: 0 | D52: 1 | E52: 4 | F52: 4 | G52: 3 | H52: pp crec. crédito
B53: Δ Depreciación vs flotación (− = suavizada por banda/intervención) | C53: 0 | D53: 0 | E53: 0 | F53: 0 | G53: 0 | H53: pp
B54: Δ Financiamiento externo concesional adicional | C54: 0 | D54: 0 | E54: 0 | F54: 0 | G54: 0 | H54: US$ mn
B55: Ventas netas de divisas para sostener banda/suavizar | C55: 0 | D55: 0 | E55: 0 | F55: 0 | G55: 0 | H55: US$ mn
B56: Régimen cambiario (0 = flotación FMI · 0,5 = flotación administrada con reglas · 1 = banda) | D56: 0
B59: 3. E3 Banda cambiaria
B60: Banda deslizante explícita (±7,5%) con intervención en los bordes para suavizar la depreciación y el traspaso a precios. Pregunta: ¿una banda administra mejor la volatilidad? Costo: reservas.
B61: Palanca | C61: 2025 | D61: 2026 | E61: 2027 | F61: 2028 | G61: 2029 | H61: Unidad
B62: Δ Inversión pública productiva | C62: 0 | D62: 0 | E62: 0 | F62: 0 | G62: 0 | H62: pp PIB
B63: Δ Gasto corriente (salarios, bienes y servicios, transferencias a EP) | C63: 0 | D63: 0 | E63: 0 | F63: 0 | G63: 0 | H63: pp PIB
B64: Δ Subsidio a combustibles vs senda FMI | C64: 0 | D64: 0 | E64: 0 | F64: 0 | G64: 0 | H64: pp PIB
B65: Δ Asistencia social focalizada | C65: 0 | D65: 0 | E65: 0 | F65: 0 | G65: 0 | H65: pp PIB
B66: Δ Recaudación potencial: anti-evasión / administración | C66: 0 | D66: 0 | E66: 0 | F66: 0 | G66: 0 | H66: pp PIB
B67: Δ Recaudación potencial: progresividad (renta, patrimonio) | C67: 0 | D67: 0 | E67: 0 | F67: 0 | G67: 0 | H67: pp PIB
B68: Δ Recaudación potencial: revisión de exenciones | C68: 0 | D68: 0 | E68: 0 | F68: 0 | G68: 0 | H68: pp PIB
B69: Δ Crecimiento de la base monetaria vs programa | C69: 0 | D69: 0 | E69: 0 | F69: 0 | G69: 0 | H69: pp
B70: Δ Crédito productivo dirigido (encaje diferenciado, garantías) | C70: 0 | D70: 0 | E70: 0 | F70: 0 | G70: 0 | H70: pp crec. crédito
B71: Δ Depreciación vs flotación (− = suavizada por banda/intervención) | C71: 0 | D71: -2 | E71: -4 | F71: -2 | G71: -1 | H71: pp
B72: Δ Financiamiento externo concesional adicional | C72: 0 | D72: 0 | E72: 0 | F72: 0 | G72: 0 | H72: US$ mn
B73: Ventas netas de divisas para sostener banda/suavizar | C73: 0 | D73: 150 | E73: 500 | F73: 300 | G73: 200 | H73: US$ mn
B74: Régimen cambiario (0 = flotación FMI · 0,5 = flotación administrada con reglas · 1 = banda) | D74: 1
B77: 4. E4 Tributaria progresiva
B78: Adelanta la movilización de ingresos a 2027: lucha contra evasión (IVA, facturación), progresividad (renta personal, patrimonio, rentas financieras) y revisión de exenciones 2025–26. Pregunta: ¿qué combinación recauda más con menor daño productivo?
B79: Palanca | C79: 2025 | D79: 2026 | E79: 2027 | F79: 2028 | G79: 2029 | H79: Unidad
B80: Δ Inversión pública productiva | C80: 0 | D80: 0 | E80: 0 | F80: 0 | G80: 0 | H80: pp PIB
B81: Δ Gasto corriente (salarios, bienes y servicios, transferencias a EP) | C81: 0 | D81: 0 | E81: 0 | F81: 0 | G81: 0 | H81: pp PIB
B82: Δ Subsidio a combustibles vs senda FMI | C82: 0 | D82: 0 | E82: 0 | F82: 0 | G82: 0 | H82: pp PIB
B83: Δ Asistencia social focalizada | C83: 0 | D83: 0 | E83: 0 | F83: 0 | G83: 0 | H83: pp PIB
B84: Δ Recaudación potencial: anti-evasión / administración | C84: 0 | D84: 0.2 | E84: 0.5 | F84: 0.8 | G84: 1 | H84: pp PIB
B85: Δ Recaudación potencial: progresividad (renta, patrimonio) | C85: 0 | D85: 0 | E85: 0.3 | F85: 0.5 | G85: 0.6 | H85: pp PIB
B86: Δ Recaudación potencial: revisión de exenciones | C86: 0 | D86: 0 | E86: 0.4 | F86: 0.5 | G86: 0.5 | H86: pp PIB
B87: Δ Crecimiento de la base monetaria vs programa | C87: 0 | D87: 0 | E87: 0 | F87: 0 | G87: 0 | H87: pp
B88: Δ Crédito productivo dirigido (encaje diferenciado, garantías) | C88: 0 | D88: 0 | E88: 0 | F88: 0 | G88: 0 | H88: pp crec. crédito
B89: Δ Depreciación vs flotación (− = suavizada por banda/intervención) | C89: 0 | D89: 0 | E89: 0 | F89: 0 | G89: 0 | H89: pp
B90: Δ Financiamiento externo concesional adicional | C90: 0 | D90: 0 | E90: 0 | F90: 0 | G90: 0 | H90: US$ mn
B91: Ventas netas de divisas para sostener banda/suavizar | C91: 0 | D91: 0 | E91: 0 | F91: 0 | G91: 0 | H91: US$ mn
B92: Régimen cambiario (0 = flotación FMI · 0,5 = flotación administrada con reglas · 1 = banda) | D92: 0
B95: 5. E5 Protección social
B96: Desmonte gradual del subsidio (diésel productivo focalizado en 2027–28) y mayor asistencia social, compensados con recorte de gasto corriente y apoyo del Banco Mundial. Pregunta: ¿menor costo social del ajuste?
B97: Palanca | C97: 2025 | D97: 2026 | E97: 2027 | F97: 2028 | G97: 2029 | H97: Unidad
B98: Δ Inversión pública productiva | C98: 0 | D98: 0 | E98: 0 | F98: 0 | G98: 0 | H98: pp PIB
B99: Δ Gasto corriente (salarios, bienes y servicios, transferencias a EP) | C99: 0 | D99: -0.2 | E99: -0.4 | F99: -0.3 | G99: -0.2 | H99: pp PIB
B100: Δ Subsidio a combustibles vs senda FMI | C100: 0 | D100: 0 | E100: 0.8 | F100: 0.3 | G100: 0 | H100: pp PIB
B101: Δ Asistencia social focalizada | C101: 0 | D101: 0.2 | E101: 0.4 | F101: 0.3 | G101: 0.2 | H101: pp PIB
B102: Δ Recaudación potencial: anti-evasión / administración | C102: 0 | D102: 0 | E102: 0 | F102: 0 | G102: 0 | H102: pp PIB
B103: Δ Recaudación potencial: progresividad (renta, patrimonio) | C103: 0 | D103: 0 | E103: 0 | F103: 0 | G103: 0 | H103: pp PIB
B104: Δ Recaudación potencial: revisión de exenciones | C104: 0 | D104: 0 | E104: 0 | F104: 0 | G104: 0 | H104: pp PIB
B105: Δ Crecimiento de la base monetaria vs programa | C105: 0 | D105: 0 | E105: 0 | F105: 0 | G105: 0 | H105: pp
B106: Δ Crédito productivo dirigido (encaje diferenciado, garantías) | C106: 0 | D106: 0 | E106: 0 | F106: 0 | G106: 0 | H106: pp crec. crédito
B107: Δ Depreciación vs flotación (− = suavizada por banda/intervención) | C107: 0 | D107: 0 | E107: 0 | F107: 0 | G107: 0 | H107: pp
B108: Δ Financiamiento externo concesional adicional | C108: 0 | D108: 0 | E108: 200 | F108: 100 | G108: 0 | H108: US$ mn
B109: Ventas netas de divisas para sostener banda/suavizar | C109: 0 | D109: 0 | E109: 0 | F109: 0 | G109: 0 | H109: US$ mn
B110: Régimen cambiario (0 = flotación FMI · 0,5 = flotación administrada con reglas · 1 = banda) | D110: 0
B113: 6. E6 Alternativo integrado
B114: Combinación eficiente: 2026 intacto para cumplir metas; desde 2027 inversión productiva + reforma tributaria progresiva/antievasión + recorte de gasto corriente y reestructuración de EP + crédito productivo neutral en base monetaria + flotación administrada con reglas + red social reforzada.
...

Sheet Motor
B2: Motor de cálculo por escenario (no editar: fórmulas)
B3: Columna 2025 = condición inicial (desvíos nulos). Desvíos (Δ) respecto de la senda FMI de Datos_FMI. Bs mn salvo indicación.
B5: 0. Base FMI
B6: Variable | C6: 2025 | D6: 2026 | E6: 2027 | F6: 2028 | G6: 2029 | H6: Unidad
B7: Palancas efectivas
B8: Inversión pública productiva (efectiva) | C8: 0 | D8: =Palancas!D8*ef26 -> 0 | E8: =Palancas!E8*1 -> 0 | F8: =Palancas!F8*1 -> 0 | G8: =Palancas!G8*1 -> 0 | H8: pp PIB
B9: Gasto corriente (efectivo) | C9: 0 | D9: =Palancas!D9*ef26 -> 0 | E9: =Palancas!E9*1 -> 0 | F9: =Palancas!F9*1 -> 0 | G9: =Palancas!G9*1 -> 0 | H9: pp PIB
B10: Subsidio combustibles (efectivo) | C10: 0 | D10: =Palancas!D10*ef26 -> 0 | E10: =Palancas!E10*1 -> 0 | F10: =Palancas!F10*1 -> 0 | G10: =Palancas!G10*1 -> 0 | H10: pp PIB
B11: Asistencia social (efectiva) | C11: 0 | D11: =Palancas!D11*ef26 -> 0 | E11: =Palancas!E11*1 -> 0 | F11: =Palancas!F11*1 -> 0 | G11: =Palancas!G11*1 -> 0 | H11: pp PIB
B12: Recaudación anti-evasión realizada | C12: 0 | D12: =Palancas!D12*ef26*r_tev -> 0 | E12: =Palancas!E12*1*r_tev -> 0 | F12: =Palancas!F12*1*r_tev -> 0 | G12: =Palancas!G12*1*r_tev -> 0 | H12: pp PIB
B13: Recaudación progresiva realizada | C13: 0 | D13: =Palancas!D13*ef26*r_tpr -> 0 | E13: =Palancas!E13*1*r_tpr -> 0 | F13: =Palancas!F13*1*r_tpr -> 0 | G13: =Palancas!G13*1*r_tpr -> 0 | H13: pp PIB
B14: Recaudación por exenciones realizada | C14: 0 | D14: =Palancas!D14*ef26*r_tex -> 0 | E14: =Palancas!E14*1*r_tex -> 0 | F14: =Palancas!F14*1*r_tex -> 0 | G14: =Palancas!G14*1*r_tex -> 0 | H14: pp PIB
B15: Δ crecimiento base monetaria (efectivo) | C15: 0 | D15: =Palancas!D15*ef26 -> 0 | E15: =Palancas!E15*1 -> 0 | F15: =Palancas!F15*1 -> 0 | G15: =Palancas!G15*1 -> 0 | H15: pp
B16: Crédito productivo dirigido (efectivo) | C16: 0 | D16: =Palancas!D16*ef26 -> 0 | E16: =Palancas!E16*1 -> 0 | F16: =Palancas!F16*1 -> 0 | G16: =Palancas!G16*1 -> 0 | H16: pp
B17: Δ depreciación por palanca (efectiva) | C17: 0 | D17: =Palancas!D17*ef26 -> 0 | E17: =Palancas!E17*1 -> 0 | F17: =Palancas!F17*1 -> 0 | G17: =Palancas!G17*1 -> 0 | H17: pp
B18: Financiamiento externo adicional | C18: 0 | D18: =Palancas!D18 -> 0 | E18: =Palancas!E18 -> 0 | F18: =Palancas!F18 -> 0 | G18: =Palancas!G18 -> 0 | H18: US$ mn
B19: Intervención cambiaria (ventas) | C19: 0 | D19: =Palancas!D19 -> 0 | E19: =Palancas!E19 -> 0 | F19: =Palancas!F19 -> 0 | G19: =Palancas!G19 -> 0 | H19: US$ mn
B20: Bloque fiscal
B21: Δ Gasto primario discrecional | C21: =C8+C9+C10+C11 -> 0 | D21: =D8+D9+D10+D11 -> 0 | E21: =E8+E9+E10+E11 -> 0 | F21: =F8+F9+F10+F11 -> 0 | G21: =G8+G9+G10+G11 -> 0 | H21: pp PIB
B22: Δ Ingresos discrecionales | C22: =C12+C13+C14 -> 0 | D22: =D12+D13+D14 -> 0 | E22: =E12+E13+E14 -> 0 | F22: =F12+F13+F14 -> 0 | G22: =G12+G13+G14 -> 0 | H22: pp PIB
B23: Δ Saldo primario discrecional | C23: =C22-C21 -> 0 | D23: =D22-D21 -> 0 | E23: =E22-E21 -> 0 | F23: =F22-F21 -> 0 | G23: =G22-G21 -> 0 | H23: pp PIB
B24: Crecimiento
B25: Δ crecimiento del crédito privado | C25: 0 | D25: =D16+bm_cred*D15-crowd*C41/(Datos_FMI!$F$33/100) -> 0 | E25: =E16+bm_cred*E15-crowd*D41/(Datos_FMI!$G$33/100) -> 0 | F25: =F16+bm_cred*F15-crowd*E41/(Datos_FMI!$H$33/100) -> 0 | G25: =G16+bm_cred*G15-crowd*F41/(Datos_FMI!$I$33/100) -> 0 | H25: pp
B26: Inversión adicional acumulada | C26: 0 | D26: =C26+D8 -> 0 | E26: =D26+E8 -> 0 | F26: =E26+F8 -> 0 | G26: =F26+G8 -> 0 | H26: pp PIB
B27: Penalización de credibilidad | C27: 0 | D27: =kappa*MAX(0,-D23-tol) -> 0 | E27: =kappa*MAX(0,-E23-tol) -> 0 | F27: =kappa*MAX(0,-F23-tol) -> 0 | G27: =kappa*MAX(0,-G23-tol) -> 0 | H27: pp
B28: Δ Crecimiento PIB real | C28: 0 | D28: =m_inv*D8+m_cur*D9+m_sub*D10+m_soc*D11-(m_tev*D12+m_tpr*D13+m_tex*D14)+eps_cred*D25+s_inv*C26+nu_dep*D17-D27 -> 0 | E28: =m_inv*E8+m_cur*E9+m_sub*E10+m_soc*E11-(m_tev*E12+m_tpr*E13+m_tex*E14)+eps_cred*E25+s_inv*D26+nu_dep*E17-E27 -> 0 | F28: =m_inv*F8+m_cur*F9+m_sub*F10+m_soc*F11-(m_tev*F12+m_tpr*F13+m_tex*F14)+eps_cred*F25+s_inv*E26+nu_dep*F17-F27 -> 0 | G28: =m_inv*G8+m_cur*G9+m_sub*G10+m_soc*G11-(m_tev*G12+m_tpr*G13+m_tex*G14)+eps_cred*G25+s_inv*F26+nu_dep*G17-G27 -> 0 | H28: pp
B29: Crecimiento PIB real | C29: =Datos_FMI!$E$6+C28 -> -1.6 | D29: =Datos_FMI!$F$6+D28 -> -3 | E29: =Datos_FMI!$G$6+E28 -> -1.5 | F29: =Datos_FMI!$H$6+F28 -> 0.5 | G29: =Datos_FMI!$I$6+G28 -> 2.5 | H29: %
B30: Δ nivel PIB real acumulado | C30: 0 | D30: =C30+D28 -> 0 | E30: =D30+E28 -> 0 | F30: =E30+F28 -> 0 | G30: =F30+G28 -> 0 | H30: %
B31: Saldos fiscales y financiamiento
B32: Δ Saldo primario total (incl. estabilizador) | C32: 0 | D32: =D23+auto*D28 -> 0 | E32: =E23+auto*E28 -> 0 | F32: =F23+auto*F28 -> 0 | G32: =G23+auto*G28 -> 0 | H32: pp PIB
B33: Saldo primario | C33: =Datos_FMI!$E$17+C32 -> -8.8 | D33: =Datos_FMI!$F$17+D32 -> -6.5 | E33: =Datos_FMI!$G$17+E32 -> -3 | F33: =Datos_FMI!$H$17+F32 -> -0.3 | G33: =Datos_FMI!$I$17+G32 -> 0.6 | H33: % PIB
B34: Saldo primario | C34: =Datos_FMI!$E$18+C32/100*Datos_FMI!$E$9 -> -39587 | D34: =Datos_FMI!$F$18+D32/100*Datos_FMI!$F$9 -> -32869 | E34: =Datos_FMI!$G$18+E32/100*Datos_FMI!$G$9 -> -17466 | F34: =Datos_FMI!$H$18+F32/100*Datos_FMI!$H$9 -> -1861.113 | G34: =Datos_FMI!$I$18+G32/100*Datos_FMI!$I$9 -> 4067.604 | H34: Bs mn
B35: Δ Intereses por deuda adicional | C35: 0 | D35: =r_int*C54/Datos_FMI!$F$9*100 -> 0 | E35: =r_int*D54/Datos_FMI!$G$9*100 -> 0 | F35: =r_int*E54/Datos_FMI!$H$9*100 -> 0 | G35: =r_int*F54/Datos_FMI!$I$9*100 -> 0 | H35: pp PIB
B36: Δ Saldo global | C36: 0 | D36: =D32-D35 -> 0 | E36: =E32-E35 -> 0 | F36: =F32-F35 -> 0 | G36: =G32-G35 -> 0 | H36: pp PIB
B37: Saldo global | C37: =Datos_FMI!$E$19+C36 -> -11.4 | D37: =Datos_FMI!$F$19+D36 -> -9.2 | E37: =Datos_FMI!$G$19+E36 -> -6.7 | F37: =Datos_FMI!$H$19+F36 -> -4 | G37: =Datos_FMI!$I$19+G36 -> -3.2 | H37: % PIB
B38: Necesidad adicional de financiamiento (+) / ahorro (−) | C38: 0 | D38: =-D36/100*Datos_FMI!$F$9 -> 0 | E38: =-E36/100*Datos_FMI!$G$9 -> 0 | F38: =-F36/100*Datos_FMI!$H$9 -> 0 | G38: =-G36/100*Datos_FMI!$I$9 -> 0 | H38: Bs mn
B39: Financiamiento externo adicional | C39: 0 | D39: =D18*D46 -> 0 | E39: =E18*E46 -> 0 | F39: =F18*F46 -> 0 | G39: =G18*G46 -> 0 | H39: Bs mn
B40: Financiamiento interno de mercado (Gestora/bancos) | C40: 0 | D40: =MIN(cap_dom/100*Datos_FMI!$F$9,MAX(0,D38-D39)) -> 0 | E40: =MIN(cap_dom/100*Datos_FMI!$G$9,MAX(0,E38-E39)) -> 0 | F40: =MIN(cap_dom/100*Datos_FMI!$H$9,MAX(0,F38-F39)) -> 0 | G40: =MIN(cap_dom/100*Datos_FMI!$I$9,MAX(0,G38-G39)) -> 0 | H40: Bs mn
B41: Financiamiento interno de mercado | C41: 0 | D41: =D40/Datos_FMI!$F$9*100 -> 0 | E41: =E40/Datos_FMI!$G$9*100 -> 0 | F41: =F40/Datos_FMI!$H$9*100 -> 0 | G41: =G40/Datos_FMI!$I$9*100 -> 0 | H41: pp PIB
B42: Brecha no financiada = crédito BCB requerido | C42: 0 | D42: =MAX(0,D38-D39-D40) -> 0 | E42: =MAX(0,E38-E39-E40) -> 0 | F42: =MAX(0,F38-F39-F40) -> 0 | G42: =MAX(0,G38-G39-G40) -> 0 | H42: Bs mn
B43: Precios y tipo de cambio
B44: Δ depreciación total | C44: 0 | D44: =D17+bm_dep*D15 -> 0 | E44: =E17+bm_dep*E15 -> 0 | F44: =F17+bm_dep*F15 -> 0 | G44: =G17+bm_dep*G15 -> 0 | H44: pp
B45: Δ depreciación acumulada | C45: 0 | D45: =C45+D44 -> 0 | E45: =D45+E44 -> 0 | F45: =E45+F44 -> 0 | G45: =F45+G44 -> 0 | H45: %
B46: Tipo de cambio promedio | C46: =12.8 -> 12.8 | D46: =Datos_FMI!$F$42*(1+D45/100) -> 9.4046359 | E46: =Datos_FMI!$G$42*(1+E45/100) -> 13.163316 | F46: =Datos_FMI!$H$42*(1+F45/100) -> 13.372087 | G46: =Datos_FMI!$I$42*(1+G45/100) -> 13.568337 | H46: Bs/US$
B47: Δ Inflación | C47: 0 | D47: =-phi_sub*(D10-C10)+mu_bm*(D15+D42/Datos_FMI!$F$34*100)+eta*D28+psi*D44+tax_pi*D12 -> 0 | E47: =-phi_sub*(E10-D10)+mu_bm*(E15+E42/Datos_FMI!$G$34*100)+eta*E28+psi*E44+tax_pi*E12 -> 0 | F47: =-phi_sub*(F10-E10)+mu_bm*(F15+F42/Datos_FMI!$H$34*100)+eta*F28+psi*F44+tax_pi*F12 -> 0 | G47: =-phi_sub*(G10-F10)+mu_bm*(G15+G42/Datos_FMI!$I$34*100)+eta*G28+psi*G44+tax_pi*G12 -> 0 | H47: pp
B48: Inflación promedio | C48: =Datos_FMI!$E$7+C47 -> 19.5 | D48: =Datos_FMI!$F$7+D47 -> 12.7 | E48: =Datos_FMI!$G$7+E47 -> 15.8 | F48: =Datos_FMI!$H$7+F47 -> 8.2 | G48: =Datos_FMI!$I$7+G47 -> 7.3 | H48: %
B49: Inflación fin de período | C49: =Datos_FMI!$E$8+C47 -> 20.4 | D49: =Datos_FMI!$F$8+D47 -> 14.2 | E49: =Datos_FMI!$G$8+E47 -> 10.7 | F49: =Datos_FMI!$H$8+F47 -> 8.7 | G49: =Datos_FMI!$I$8+G47 -> 6.2 | H49: %
B50: Δ nivel de precios acumulado | C50: 0 | D50: =C50+D47 -> 0 | E50: =D50+E47 -> 0 | F50: =E50+F47 -> 0 | G50: =F50+G47 -> 0 | H50: %
B51: PIB nominal del escenario | C51: =Datos_FMI!$E$9*(1+C30/100)*(1+C50/100) -> 447553 | D51: =Datos_FMI!$F$9*(1+D30/100)*(1+D50/100) -> 506391 | E51: =Datos_FMI!$G$9*(1+E30/100)*(1+E50/100) -> 578299 | F51: =Datos_FMI!$H$9*(1+F30/100)*(1+F50/100) -> 620371 | G51: =Datos_FMI!$I$9*(1+G30/100)*(1+G50/100) -> 677934 | H51: Bs mn
B52: Deuda
B53: Deuda adicional acumulada por flujos | C53: 0 | D53: =C53+D38 -> 0 | E53: =D53+E38 -> 0 | F53: =E53+F38 -> 0 | G53: =F53+G38 -> 0 | H53: Bs mn
B54: Δ Deuda total (flujos + valoración cambiaria) | C54: 0 | D54: =D53+Datos_FMI!$F$22*D45/100 -> 0 | E54: =E53+Datos_FMI!$G$22*E45/100 -> 0 | F54: =F53+Datos_FMI!$H$22*F45/100 -> 0 | G54: =G53+Datos_FMI!$I$22*G45/100 -> 0 | H54: Bs mn
B55: Deuda bruta SPNF | C55: =(Datos_FMI!$E$21+C54)/C51*100 -> 83.316836 | D55: =(Datos_FMI!$F$21+D54)/D51*100 -> 100.47769 | E55: =(Datos_FMI!$G$21+E54)/E51*100 -> 95.361223 | F55: =(Datos_FMI!$H$21+F54)/F51*100 -> 93.185529 | G55: =(Datos_FMI!$I$21+G54)/G51*100 -> 89.203374 | H55: % PIB
B56: Reservas
B57: Δ RIN del año (flujo) | C57: 0 | D57: =D18-D19-imp_el*D28/100*Datos_FMI!$F$24-sub_leak*D10/100*Datos_FMI!$F$41-bm_flight*D15-monet_leak*D42/D46 -> 0 | E57: =E18-E19-imp_el*E28/100*Datos_FMI!$G$24-sub_leak*E10/100*Datos_FMI!$G$41-bm_flight*E15-monet_leak*E42/E46 -> 0 | F57: =F18-F19-imp_el*F28/100*Datos_FMI!$H$24-sub_leak*F10/100*Datos_FMI!$H$41-bm_flight*F15-monet_leak*F42/F46 -> 0 | G57: =G18-G19-imp_el*G28/100*Datos_FMI!$I$24-sub_leak*G10/100*Datos_FMI!$I$41-bm_flight*G15-monet_leak*G42/G46 -> 0 | H57: US$ mn
B58: Δ RIN acumulada vs FMI | C58: 0 | D58: =C58+D57 -> 0 | E58: =D58+E57 -> 0 | F58: =E58+F57 -> 0 | G58: =F58+G57 -> 0 | H58: US$ mn
B59: RIN del programa (stock) | C59: =Datos_FMI!$E$31+C58 -> -2990 | D59: =Datos_FMI!$F$31+D58 -> -581 | E59: =Datos_FMI!$G$31+E58 -> 744 | F59: =Datos_FMI!$H$31+F58 -> 1304 | G59: =Datos_FMI!$I$31+G58 -> 1878 | H59: US$ mn
B60: RIB del programa | C60: =Datos_FMI!$E$28+C58 -> 627 | D60: =Datos_FMI!$F$28+D58 -> 2458 | E60: =Datos_FMI!$G$28+E58 -> 3982 | F60: =Datos_FMI!$H$28+F58 -> 4690 | G60: =Datos_FMI!$I$28+G58 -> 5527 | H60: US$ mn
B61: RIB programa / métrica ARA | C61: =Datos_FMI!$E$29*C60/Datos_FMI!$E$28 -> 10.9 | D61: =Datos_FMI!$F$29*D60/Datos_FMI!$F$28 -> 53.4 | E61: =Datos_FMI!$G$29*E60/Datos_FMI!$G$28 -> 86.1 | F61: =Datos_FMI!$H$29*F60/Datos_FMI!$H$28 -> 100.1 | G61: =Datos_FMI!$I$29*G60/Datos_FMI!$I$28 -> 112.3 | H61: %
B62: Dinero, crédito y metas monetarias
B63: Crecimiento del crédito privado | C63: =Datos_FMI!$E$32+C25 -> 3.1 | D63: =Datos_FMI!$F$32+D25 -> 4 | E63: =Datos_FMI!$G$32+E25 -> 7.3 | F63: =Datos_FMI!$H$32+F25 -> 7.3 | G63: =Datos_FMI!$I$32+G25 -> 9.5 | H63: %
B64: Δ base monetaria acumulada | C64: 0 | D64: =C64+D15 -> 0 | E64: =D64+E15 -> 0 | F64: =E64+F15 -> 0 | G64: =F64+G15 -> 0 | H64: %
B65: Monetización acumulada | C65: 0 | D65: =C65+D42 -> 0 | E65: =D65+E42 -> 0 | F65: =E65+F42 -> 0 | G65: =F65+G42 -> 0 | H65: Bs mn
B66: Base monetaria (indicador meta) | C66: =Datos_FMI!$E$34 -> 132269 | D66: =meta_bm*(1+D64/100)+D65 -> 133900 | E66: =Datos_FMI!$G$34*(1+E64/100)+E65 -> 148333 | F66: =Datos_FMI!$H$34*(1+F64/100)+F65 -> 161304 | G66: =Datos_FMI!$I$34*(1+G64/100)+G65 -> 177013 | H66: Bs mn
B67: Social, empleo y distribución
B68: Gasto en asistencia social | C68: =Datos_FMI!$E$14+C11/100*Datos_FMI!$E$9 -> 5525 | D68: =Datos_FMI!$F$14+D11/100*Datos_FMI!$F$9 -> 10890 | E68: =Datos_FMI!$G$14+E11/100*Datos_FMI!$G$9 -> 12722.578 | F68: =Datos_FMI!$H$14+F11/100*Datos_FMI!$H$9 -> 8064.823 | G68: =Datos_FMI!$I$14+G11/100*Datos_FMI!$I$9 -> 8813.142 | H68: Bs mn
B69: Δ Empleo vs FMI | C69: 0 | D69: =emp_el*D30/100*pea -> 0 | E69: =emp_el*E30/100*pea -> 0 | F69: =emp_el*F30/100*pea -> 0 | G69: =emp_el*G30/100*pea -> 0 | H69: miles
B70: Δ Pobreza vs FMI | C70: 0 | D70: =-pov_g*D30-pov_soc*D11+pov_pi*D47-pov_sub*D10 -> 0 | E70: =-pov_g*E30-pov_soc*E11+pov_pi*E47-pov_sub*E10 -> 0 | F70: =-pov_g*F30-pov_soc*F11+pov_pi*F47-pov_sub*F10 -> 0 | G70: =-pov_g*G30-pov_soc*G11+pov_pi*G47-pov_sub*G10 -> 0 | H70: pp
B71: Δ Gini vs FMI | C71: 0 | D71: =-gini_tpr*D13-gini_soc*D11 -> 0 | E71: =-gini_tpr*E13-gini_soc*E11 -> 0 | F71: =-gini_tpr*F13-gini_soc*F11 -> 0 | G71: =-gini_tpr*G13-gini_soc*G11 -> 0 | H71: pts
B77: 1. E1 Fiscal gradual
B78: Variable | C78: 2025 | D78: 2026 | E78: 2027 | F78: 2028 | G78: 2029 | H78: Unidad
B79: Palancas efectivas
B80: Inversión pública productiva (efectiva) | C80: 0 | D80: =Palancas!D26*ef26 -> 0.125 | E80: =Palancas!E26*1 -> 1 | F80: =Palancas!F26*1 -> 0.8 | G80: =Palancas!G26*1 -> 0.5 | H80: pp PIB
B81: Gasto corriente (efectivo) | C81: 0 | D81: =Palancas!D27*ef26 -> 0 | E81: =Palancas!E27*1 -> 0 | F81: =Palancas!F27*1 -> 0 | G81: =Palancas!G27*1 -> 0 | H81: pp PIB
B82: Subsidio combustibles (efectivo) | C82: 0 | D82: =Palancas!D28*ef26 -> 0 | E82: =Palancas!E28*1 -> 0 | F82: =Palancas!F28*1 -> 0 | G82: =Palancas!G28*1 -> 0 | H82: pp PIB
B83: Asistencia social (efectiva) | C83: 0 | D83: =Palancas!D29*ef26 -> 0 | E83: =Palancas!E29*1 -> 0 | F83: =Palancas!F29*1 -> 0 | G83: =Palancas!G29*1 -> 0 | H83: pp PIB
B84: Recaudación anti-evasión realizada | C84: 0 | D84: =Palancas!D30*ef26*r_tev -> 0 | E84: =Palancas!E30*1*r_tev -> 0 | F84: =Palancas!F30*1*r_tev -> 0 | G84: =Palancas!G30*1*r_tev -> 0 | H84: pp PIB
B85: Recaudación progresiva realizada | C85: 0 | D85: =Palancas!D31*ef26*r_tpr -> 0 | E85: =Palancas!E31*1*r_tpr -> 0 | F85: =Palancas!F31*1*r_tpr -> 0 | G85: =Palancas!G31*1*r_tpr -> 0 | H85: pp PIB
B86: Recaudación por exenciones realizada | C86: 0 | D86: =Palancas!D32*ef26*r_tex -> 0 | E86: =Palancas!E32*1*r_tex -> 0 | F86: =Palancas!F32*1*r_tex -> 0 | G86: =Palancas!G32*1*r_tex -> 0 | H86: pp PIB
B87: Δ crecimiento base monetaria (efectivo) | C87: 0 | D87: =Palancas!D33*ef26 -> 0 | E87: =Palancas!E33*1 -> 0 | F87: =Palancas!F33*1 -> 0 | G87: =Palancas!G33*1 -> 0 | H87: pp
B88: Crédito productivo dirigido (efectivo) | C88: 0 | D88: =Palancas!D34*ef26 -> 0 | E88: =Palancas!E34*1 -> 0 | F88: =Palancas!F34*1 -> 0 | G88: =Palancas!G34*1 -> 0 | H88: pp
B89: Δ depreciación por palanca (efectiva) | C89: 0 | D89: =Palancas!D35*ef26 -> 0 | E89: =Palancas!E35*1 -> 0 | F89: =Palancas!F35*1 -> 0 | G89: =Palancas!G35*1 -> 0 | H89: pp
B90: Financiamiento externo adicional | C90: 0 | D90: =Palancas!D36 -> 100 | E90: =Palancas!E36 -> 500 | F90: =Palancas!F36 -> 400 | G90: =Palancas!G36 -> 200 | H90: US$ mn
B91: Intervención cambiaria (ventas) | C91: 0 | D91: =Palancas!D37 -> 0 | E91: =Palancas!E37 -> 0 | F91: =Palancas!F37 -> 0 | G91: =Palancas!G37 -> 0 | H91: US$ mn
B92: Bloque fiscal
B93: Δ Gasto primario discrecional | C93: =C80+C81+C82+C83 -> 0 | D93: =D80+D81+D82+D83 -> 0.125 | E93: =E80+E81+E82+E83 -> 1 | F93: =F80+F81+F82+F83 -> 0.8 | G93: =G80+G81+G82+G83 -> 0.5 | H93: pp PIB
B94: Δ Ingresos discrecionales | C94: =C84+C85+C86 -> 0 | D94: =D84+D85+D86 -> 0 | E94: =E84+E85+E86 -> 0 | F94: =F84+F85+F86 -> 0 | G94: =G84+G85+G86 -> 0 | H94: pp PIB
B95: Δ Saldo primario discrecional | C95: =C94-C93 -> 0 | D95: =D94-D93 -> -0.125 | E95: =E94-E93 -> -1 | F95: =F94-F93 -> -0.8 | G95: =G94-G93 -> -0.5 | H95: pp PIB
B96: Crecimiento
B97: Δ crecimiento del crédito privado | C97: 0 | D97: =D88+bm_cred*D87-crowd*C113/(Datos_FMI!$F$33/100) -> 0 | E97: =E88+bm_cred*E87-crowd*D113/(Datos_FMI!$G$33/100) -> 0 | F97: =F88+bm_cred*F87-crowd*E113/(Datos_FMI!$H$33/100) -> 0 | G97: =G88+bm_cred*G87-crowd*F113/(Datos_FMI!$I$33/100) -> 0 | H97: pp
B98: Inversión adicional acumulada | C98: 0 | D98: =C98+D80 -> 0.125 | E98: =D98+E80 -> 1.125 | F98: =E98+F80 -> 1.925 | G98: =F98+G80 -> 2.425 | H98: pp PIB
B99: Penalización de credibilidad | C99: 0 | D99: =kappa*MAX(0,-D95-tol) -> 0 | E99: =kappa*MAX(0,-E95-tol) -> 0.15 | F99: =kappa*MAX(0,-F95-tol) -> 0.09 | G99: =kappa*MAX(0,-G95-tol) -> 0 | H99: pp
B100: Δ Crecimiento PIB real | C100: 0 | D100: =m_inv*D80+m_cur*D81+m_sub*D82+m_soc*D83-(m_tev*D84+m_tpr*D85+m_tex*D86)+eps_cred*D97+s_inv*C98+nu_dep*D89-D99 -> 0.0875 | E100: =m_inv*E80+m_cur*E81+m_sub*E82+m_soc*E83-(m_tev*E84+m_tpr*E85+m_tex*E86)+eps_cred*E97+s_inv*D98+nu_dep*E89-E99 -> 0.5625 | F100: =m_inv*F80+m_cur*F81+m_sub*F82+m_soc*F83-(m_tev*F84+m_tpr*F85+m_tex*F86)+eps_cred*F97+s_inv*E98+nu_dep*F89-F99 -> 0.5825 | G100: =m_inv*G80+m_cur*G81+m_sub*G82+m_soc*G83-(m_tev*G84+m_tpr*G85+m_tex*G86)+eps_cred*G97+s_inv*F98+nu_dep*G89-G99 -> 0.5425 | H100: pp
B101: Crecimiento PIB real | C101: =Datos_FMI!$E$6+C100 -> -1.6 | D101: =Datos_FMI!$F$6+D100 -> -2.9125 | E101: =Datos_FMI!$G$6+E100 -> -0.9375 | F101: =Datos_FMI!$H$6+F100 -> 1.0825 | G101: =Datos_FMI!$I$6+G100 -> 3.0425 | H101: %
B102: Δ nivel PIB real acumulado | C102: 0 | D102: =C102+D100 -> 0.0875 | E102: =D102+E100 -> 0.65 | F102: =E102+F100 -> 1.2325 | G102: =F102+G100 -> 1.775 | H102: %
B103: Saldos fiscales y financiamiento
B104: Δ Saldo primario total (incl. estabilizador) | C104: 0 | D104: =D95+auto*D100 -> -0.1075 | E104: =E95+auto*E100 -> -0.8875 | F104: =F95+auto*F100 -> -0.6835 | G104: =G95+auto*G100 -> -0.3915 | H104: pp PIB
B105: Saldo primario | C105: =Datos_FMI!$E$17+C104 -> -8.8 | D105: =Datos_FMI!$F$17+D104 -> -6.6075 | E105: =Datos_FMI!$G$17+E104 -> -3.8875 | F105: =Datos_FMI!$H$17+F104 -> -0.9835 | G105: =Datos_FMI!$I$17+G104 -> 0.2085 | H105: % PIB
B106: Saldo primario | C106: =Datos_FMI!$E$18+C104/100*Datos_FMI!$E$9 -> -39587 | D106: =Datos_FMI!$F$18+D104/100*Datos_FMI!$F$9 -> -33413.37 | E106: =Datos_FMI!$G$18+E104/100*Datos_FMI!$G$9 -> -22598.404 | F106: =Datos_FMI!$H$18+F104/100*Datos_FMI!$H$9 -> -6101.3488 | G106: =Datos_FMI!$I$18+G104/100*Datos_FMI!$I$9 -> 1413.4924 | H106: Bs mn
B107: Δ Intereses por deuda adicional | C107: 0 | D107: =r_int*C126/Datos_FMI!$F$9*100 -> 0 | E107: =r_int*D126/Datos_FMI!$G$9*100 -> 0.0061186464 | F107: =r_int*E126/Datos_FMI!$H$9*100 -> 0.059849714 | G107: =r_int*F126/Datos_FMI!$I$9*100 -> 0.098983008 | H107: pp PIB
...

Sheet Shocks
B2: Quinta misión: el cisne negro boliviano (shocks hipotéticos)
B3: Impacto sobre el escenario elegido en el Dashboard. Año del shock = 100%; año siguiente = persistencia. La respuesta mitiga crecimiento e inflación a un costo fiscal.
B5: Parámetros del shock | C5: Shock petrolero (+25%) | D5: Crisis de confianza | E5: Bloqueos (3 semanas) | F5: Crisis bancaria | G5: Freno legislativo
B6: Impacto en crecimiento (pp) | C6: -0.3 | D6: -0.5 | E6: -0.6 | F6: -0.8 | G6: -0.3
B7: Impacto directo en inflación (pp) | C7: 0 | D7: 0 | E7: 1.5 | F7: 0.5 | G7: 0
B8: Impacto directo en saldo primario (pp PIB) | C8: 0 | D8: 0 | E8: -0.1 | F8: 0 | G8: 0
B9: Impacto directo en RIN (US$ mn) | C9: 0 | D9: 0 | E9: -100 | F9: -300 | G9: 0
B10: Impacto en crédito privado (pp) | C10: 0 | D10: -2 | E10: 0 | F10: -6 | G10: 0
B11: Liquidez de emergencia BCB (Bs mn, base monetaria) | C11: 0 | D11: 0 | E11: 0 | F11: 3000 | G11: 0
B12: Costo de recapitalización (pp PIB, deuda) | C12: 0 | D12: 0 | E12: 0 | F12: 0.8 | G12: 0
B13: Persistencia al año siguiente (fracción) | C13: 0.6 | D13: 0.3 | E13: 0 | F13: 0.5 | G13: 1
B14: Mitigación con respuesta (fracción de g y π evitada) | C14: 0.4 | D14: 0.4 | E14: 0.5 | F14: 0.5 | G14: 0.3
B15: Costo fiscal de la respuesta (pp PIB) | C15: 0.15 | D15: 0 | E15: 0.1 | F15: 0.2 | G15: 0
B16: Alza del precio internacional del petróleo | C16: 0.25 | D16: 0 | E16: 0 | F16: 0 | G16: 0
B17: Peso efectivo (directo+indirecto) de combustibles en IPC | C17: 0.08 | D17: 0 | E17: 0 | F17: 0 | G17: 0
... B20: Desembolsos IFI demorados un año (US$ mn) | C20: 0 | D20: 0 | E20: 0 | F20: 0 | G20: 1000
B22: Respuesta (10 minutos) | C22: Shock petrolero (+25%) | D22: Crisis de confianza | E22: Bloqueos (3 semanas) | F22: Crisis bancaria | G22: Freno legislativo
B23: Instrumento que se usa primero | C23: Mecanismo automático de precios (DS 5652) con suavizado trimestral + bono focalizado transitorio a transporte público y productores (registro PEPE) | D23: Comunicación + subasta de divisas con reglas; alza de tasas de títulos BCB; nada de controles ni tipos múltiples | E23: Corredores humanitarios de alimentos/combustible, importación privada autorizada (DS 5644) y diálogo; reprogramar gasto | F23: Liquidez de emergencia (ALE) con garantía, intervención temprana de ASFI y plan de resolución del banco sistémico | G23: Decretos de administración tributaria (sin ley), reprogramar inversión no prioritaria y usar depósitos del SPNF en BCB
B24: Costo que se acepta | C24: Más inflación transitoria y un costo fiscal de 0,15% del PIB | D24: Depreciación y menor crédito por tasas altas | E24: Pérdida de producción del trimestre y 0,1% del PIB en compensaciones | F24: Costo de recapitalización (0,8% PIB) y expansión temporal de la base | G24: Menor inversión pública y caída de depósitos fiscales
B25: Objetivo que se protege prioritariamente | C25: Reservas y saldo primario (no volver a congelar precios) | D25: Reservas (piso de RIN) y ancla nominal | E25: Abastecimiento y precios de alimentos | F25: Depósitos y sistema de pagos | G25: Cero crédito del BCB y saldo primario
B27: Cálculo de impactos sobre el escenario seleccionado
B28: Perfil temporal | D28: 2026 | E28: 2027 | F28: 2028 | G28: 2029
B29: Perfil: Shock petrolero (+25%) | D29: =IF(2026=sel_year,1,IF(2026=sel_year+1,C$13,0)) -> 0 | E29: =IF(2027=sel_year,1,IF(2027=sel_year+1,C$13,0)) -> 1 | F29: =IF(2028=sel_year,1,IF(2028=sel_year+1,C$13,0)) -> 0.6 | G29: =IF(2029=sel_year,1,IF(2029=sel_year+1,C$13,0)) -> 0
B30: Perfil: Crisis de confianza | D30: =IF(2026=sel_year,1,IF(2026=sel_year+1,D$13,0)) -> 0 | E30: =IF(2027=sel_year,1,IF(2027=sel_year+1,D$13,0)) -> 1 | F30: =IF(2028=sel_year,1,IF(2028=sel_year+1,D$13,0)) -> 0.3 | G30: =IF(2029=sel_year,1,IF(2029=sel_year+1,D$13,0)) -> 0
B31: Perfil: Bloqueos (3 semanas) | D31: =IF(2026=sel_year,1,IF(2026=sel_year+1,E$13,0)) -> 0 | E31: =IF(2027=sel_year,1,IF(2027=sel_year+1,E$13,0)) -> 1 | F31: =IF(2028=sel_year,1,IF(2028=sel_year+1,E$13,0)) -> 0 | G31: =IF(2029=sel_year,1,IF(2029=sel_year+1,E$13,0)) -> 0
B32: Perfil: Crisis bancaria | D32: =IF(2026=sel_year,1,IF(2026=sel_year+1,F$13,0)) -> 0 | E32: =IF(2027=sel_year,1,IF(2027=sel_year+1,F$13,0)) -> 1 | F32: =IF(2028=sel_year,1,IF(2028=sel_year+1,F$13,0)) -> 0.5 | G32: =IF(2029=sel_year,1,IF(2029=sel_year+1,F$13,0)) -> 0
B33: Perfil: Freno legislativo | D33: =IF(2026=sel_year,1,IF(2026=sel_year+1,G$13,0)) -> 0 | E33: =IF(2027=sel_year,1,IF(2027=sel_year+1,G$13,0)) -> 1 | F33: =IF(2028=sel_year,1,IF(2028=sel_year+1,G$13,0)) -> 1 | G33: =IF(2029=sel_year,1,IF(2029=sel_year+1,G$13,0)) -> 0
B35: Shock petrolero (+25%) | D35: 2026 | E35: 2027 | F35: 2028 | G35: 2029
B36: Δ crecimiento (pp) | D36: =C$6*D$29*IF(2026=2026,ef26,1)*(1-IF(sel_resp="Sí",C$14,0)) -> 0 | E36: =C$6*E$29*IF(2027=2026,ef26,1)*(1-IF(sel_resp="Sí",C$14,0)) -> -0.18 | F36: =C$6*F$29*IF(2028=2026,ef26,1)*(1-IF(sel_resp="Sí",C$14,0)) -> -0.108 | G36: =C$6*G$29*IF(2029=2026,ef26,1)*(1-IF(sel_resp="Sí",C$14,0)) -> 0
B37: Δ inflación (pp) | D37: =C$16*C$17*100*(1-IF(2026=2026,1,MIN(1,MAX(0,INDEX(Motor!$D$1:$D$600,5+(sel_idx-1)*72+5))/sub_full)))*D$29*IF(2026=2026,ef26,1)*(1-IF(sel_resp="Sí",C$14,0)) -> 0 | E37: =C$16*C$17*100*(1-IF(2027=2026,1,MIN(1,MAX(0,INDEX(Motor!$E$1:$E$600,5+(sel_idx-1)*72+5))/sub_full)))*E$29*IF(2027=2026,ef26,1)*(1-IF(sel_resp="Sí",C$14,0)) -> 0.96 | F37: =C$16*C$17*100*(1-IF(2028=2026,1,MIN(1,MAX(0,INDEX(Motor!$F$1:$F$600,5+(sel_idx-1)*72+5))/sub_full)))*F$29*IF(2028=2026,ef26,1)*(1-IF(sel_resp="Sí",C$14,0)) -> 0.72 | G37: =C$16*C$17*100*(1-IF(2029=2026,1,MIN(1,MAX(0,INDEX(Motor!$G$1:$G$600,5+(sel_idx-1)*72+5))/sub_full)))*G$29*IF(2029=2026,ef26,1)*(1-IF(sel_resp="Sí",C$14,0)) -> 0
B38: Δ saldo primario (pp PIB) | D38: =-C$16*Datos_FMI!$F$26*INDEX(Motor!$D$1:$D$600,5+(sel_idx-1)*72+41)/Datos_FMI!$F$9*100*IF(2026=2026,1,MIN(1,MAX(0,INDEX(Motor!$D$1:$D$600,5+(sel_idx-1)*72+5))/sub_full))*D$29*IF(2026=2026,ef26,1)-IF(sel_resp="Sí",C$15,0)*D$29*IF(2026=2026,ef26,1) -> 0 | E38: =-C$16*Datos_FMI!$G$26*INDEX(Motor!$E$1:$E$600,5+(sel_idx-1)*72+41)/Datos_FMI!$G$9*100*IF(2027=2026,1,MIN(1,MAX(0,INDEX(Motor!$E$1:$E$600,5+(sel_idx-1)*72+5))/sub_full))*E$29*IF(2027=2026,ef26,1)-IF(sel_resp="Sí",C$15,0)*E$29*IF(2027=2026,ef26,1) -> -0.51315694 | F38: =-C$16*Datos_FMI!$H$26*INDEX(Motor!$F$1:$F$600,5+(sel_idx-1)*72+41)/Datos_FMI!$H$9*100*IF(2028=2026,1,MIN(1,MAX(0,INDEX(Motor!$F$1:$F$600,5+(sel_idx-1)*72+5))/sub_full))*F$29*IF(2028=2026,ef26,1)-IF(sel_resp="Sí",C$15,0)*F$29*IF(2028=2026,ef26,1) -> -0.09 | G38: =-C$16*Datos_FMI!$I$26*INDEX(Motor!$G$1:$G$600,5+(sel_idx-1)*72+41)/Datos_FMI!$I$9*100*IF(2029=2026,1,MIN(1,MAX(0,INDEX(Motor!$G$1:$G$600,5+(sel_idx-1)*72+5))/sub_full))*G$29*IF(2029=2026,ef26,1)-IF(sel_resp="Sí",C$15,0)*G$29*IF(2029=2026,ef26,1) -> 0
B39: Δ RIN del año (US$ mn) | D39: =-C$16*Datos_FMI!$F$26*D$29*IF(2026=2026,ef26,1) -> 0 | E39: =-C$16*Datos_FMI!$G$26*E$29*IF(2027=2026,ef26,1) -> -803.75 | F39: =-C$16*Datos_FMI!$H$26*F$29*IF(2028=2026,ef26,1) -> -466.05 | G39: =-C$16*Datos_FMI!$I$26*G$29*IF(2029=2026,ef26,1) -> 0
B40: Δ crédito privado (pp) | D40: =C$10*D$29*IF(2026=2026,ef26,1) -> 0 | E40: =C$10*E$29*IF(2027=2026,ef26,1) -> 0 | F40: =C$10*F$29*IF(2028=2026,ef26,1) -> 0 | G40: =C$10*G$29*IF(2029=2026,ef26,1) -> 0
B41: Δ base monetaria (Bs mn) | D41: =C$11*D$29*IF(2026=2026,ef26,1) -> 0 | E41: =C$11*E$29*IF(2027=2026,ef26,1) -> 0 | F41: =C$11*F$29*IF(2028=2026,ef26,1) -> 0 | G41: =C$11*G$29*IF(2029=2026,ef26,1) -> 0
B42: Δ deuda por recapitalización (pp PIB) | D42: =C$12*D$29*IF(2026=2026,ef26,1) -> 0 | E42: =C$12*E$29*IF(2027=2026,ef26,1) -> 0 | F42: =C$12*F$29*IF(2028=2026,ef26,1) -> 0 | G42: =C$12*G$29*IF(2029=2026,ef26,1) -> 0
B44: Crisis de confianza | D44: 2026 | E44: 2027 | F44: 2028 | G44: 2029
B45: Δ crecimiento (pp) | D45: =D$6*D$30*(1-IF(sel_resp="Sí",D$14,0)) -> 0 | E45: =D$6*E$30*(1-IF(sel_resp="Sí",D$14,0)) -> -0.3 | F45: =D$6*F$30*(1-IF(sel_resp="Sí",D$14,0)) -> -0.09 | G45: =D$6*G$30*(1-IF(sel_resp="Sí",D$14,0)) -> 0
B46: Δ inflación (pp) | D46: =psi*D$19*(1-2/3*INDEX(Palancas!$D$1:$D$400,5+(sel_idx-1)*18+15))*D$30*(1-IF(sel_resp="Sí",D$14,0)) -> 0 | E46: =psi*D$19*(1-2/3*INDEX(Palancas!$D$1:$D$400,5+(sel_idx-1)*18+15))*E$30*(1-IF(sel_resp="Sí",D$14,0)) -> 1.68 | F46: =psi*D$19*(1-2/3*INDEX(Palancas!$D$1:$D$400,5+(sel_idx-1)*18+15))*F$30*(1-IF(sel_resp="Sí",D$14,0)) -> 0.504 | G46: =psi*D$19*(1-2/3*INDEX(Palancas!$D$1:$D$400,5+(sel_idx-1)*18+15))*G$30*(1-IF(sel_resp="Sí",D$14,0)) -> 0
B47: Δ saldo primario (pp PIB) | D47: =D$8*D$30-IF(sel_resp="Sí",D$15,0)*D$30 -> 0 | E47: =D$8*E$30-IF(sel_resp="Sí",D$15,0)*E$30 -> 0 | F47: =D$8*F$30-IF(sel_resp="Sí",D$15,0)*F$30 -> 0 | G47: =D$8*G$30-IF(sel_resp="Sí",D$15,0)*G$30 -> 0
B48: Δ RIN del año (US$ mn) | D48: =-D$18*(0.2+0.6*INDEX(Palancas!$D$1:$D$400,5+(sel_idx-1)*18+15))*D$30 -> 0 | E48: =-D$18*(0.2+0.6*INDEX(Palancas!$D$1:$D$400,5+(sel_idx-1)*18+15))*E$30 -> -400 | F48: =-D$18*(0.2+0.6*INDEX(Palancas!$D$1:$D$400,5+(sel_idx-1)*18+15))*F$30 -> -120 | G48: =-D$18*(0.2+0.6*INDEX(Palancas!$D$1:$D$400,5+(sel_idx-1)*18+15))*G$30 -> 0
B49: Δ crédito privado (pp) | D49: =D$10*D$30 -> 0 | E49: =D$10*E$30 -> -2 | F49: =D$10*F$30 -> -0.6 | G49: =D$10*G$30 -> 0
B50: Δ base monetaria (Bs mn) | D50: =D$11*D$30 -> 0 | E50: =D$11*E$30 -> 0 | F50: =D$11*F$30 -> 0 | G50: =D$11*G$30 -> 0
B51: Δ deuda por recapitalización (pp PIB) | D51: =D$12*D$30 -> 0 | E51: =D$12*E$30 -> 0 | F51: =D$12*F$30 -> 0 | G51: =D$12*G$30 -> 0
B53: Bloqueos (3 semanas) | D53: 2026 | E53: 2027 | F53: 2028 | G53: 2029
B54: Δ crecimiento (pp) | D54: =E$6*D$31*(1-IF(sel_resp="Sí",E$14,0)) -> 0 | E54: =E$6*E$31*(1-IF(sel_resp="Sí",E$14,0)) -> -0.3 | F54: =E$6*F$31*(1-IF(sel_resp="Sí",E$14,0)) -> 0 | G54: =E$6*G$31*(1-IF(sel_resp="Sí",E$14,0)) -> 0
B55: Δ inflación (pp) | D55: =E$7*D$31*(1-IF(sel_resp="Sí",E$14,0)) -> 0 | E55: =E$7*E$31*(1-IF(sel_resp="Sí",E$14,0)) -> 0.75 | F55: =E$7*F$31*(1-IF(sel_resp="Sí",E$14,0)) -> 0 | G55: =E$7*G$31*(1-IF(sel_resp="Sí",E$14,0)) -> 0
B56: Δ saldo primario (pp PIB) | D56: =E$8*D$31-IF(sel_resp="Sí",E$15,0)*D$31 -> 0 | E56: =E$8*E$31-IF(sel_resp="Sí",E$15,0)*E$31 -> -0.2 | F56: =E$8*F$31-IF(sel_resp="Sí",E$15,0)*F$31 -> 0 | G56: =E$8*G$31-IF(sel_resp="Sí",E$15,0)*G$31 -> 0
B57: Δ RIN del año (US$ mn) | D57: =E$9*D$31 -> 0 | E57: =E$9*E$31 -> -100 | F57: =E$9*F$31 -> 0 | G57: =E$9*G$31 -> 0
B58: Δ crédito privado (pp) | D58: =E$10*D$31 -> 0 | E58: =E$10*E$31 -> 0 | F58: =E$10*F$31 -> 0 | G58: =E$10*G$31 -> 0
B59: Δ base monetaria (Bs mn) | D59: =E$11*IF(2026=sel_year,1,0) -> 0 | E59: =E$11*IF(2027=sel_year,1,0) -> 0 | F59: =E$11*IF(2028=sel_year,1,0) -> 0 | G59: =E$11*IF(2029=sel_year,1,0) -> 0
B60: Δ deuda por recapitalización (pp PIB) | D60: =E$12*IF(2026=sel_year,1,0) -> 0 | E60: =E$12*IF(2027=sel_year,1,0) -> 0 | F60: =E$12*IF(2028=sel_year,1,0) -> 0 | G60: =E$12*IF(2029=sel_year,1,0) -> 0
B62: Crisis bancaria | D62: 2026 | E62: 2027 | F62: 2028 | G62: 2029
B63: Δ crecimiento (pp) | D63: =F$6*D$32*(1-IF(sel_resp="Sí",F$14,0)) -> 0 | E63: =F$6*E$32*(1-IF(sel_resp="Sí",F$14,0)) -> -0.4 | F63: =F$6*F$32*(1-IF(sel_resp="Sí",F$14,0)) -> -0.2 | G63: =F$6*G$32*(1-IF(sel_resp="Sí",F$14,0)) -> 0
B64: Δ inflación (pp) | D64: =F$7*D$32*(1-IF(sel_resp="Sí",F$14,0)) -> 0 | E64: =F$7*E$32*(1-IF(sel_resp="Sí",F$14,0)) -> 0.25 | F64: =F$7*F$32*(1-IF(sel_resp="Sí",F$14,0)) -> 0.125 | G64: =F$7*G$32*(1-IF(sel_resp="Sí",F$14,0)) -> 0
B65: Δ saldo primario (pp PIB) | D65: =F$8*D$32-IF(sel_resp="Sí",F$15,0)*D$32 -> 0 | E65: =F$8*E$32-IF(sel_resp="Sí",F$15,0)*E$32 -> -0.2 | F65: =F$8*F$32-IF(sel_resp="Sí",F$15,0)*F$32 -> -0.1 | G65: =F$8*G$32-IF(sel_resp="Sí",F$15,0)*G$32 -> 0
B66: Δ RIN del año (US$ mn) | D66: =F$9*D$32 -> 0 | E66: =F$9*E$32 -> -300 | F66: =F$9*F$32 -> -150 | G66: =F$9*G$32 -> 0
B67: Δ crédito privado (pp) | D67: =F$10*D$32 -> 0 | E67: =F$10*E$32 -> -6 | F67: =F$10*F$32 -> -3 | G67: =F$10*G$32 -> 0
B68: Δ base monetaria (Bs mn) | D68: =F$11*IF(2026=sel_year,1,0) -> 0 | E68: =F$11*IF(2027=sel_year,1,0) -> 3000 | F68: =F$11*IF(2028=sel_year,1,0) -> 0 | G68: =F$11*IF(2029=sel_year,1,0) -> 0
B69: Δ deuda por recapitalización (pp PIB) | D69: =F$12*IF(2026=sel_year,1,0) -> 0 | E69: =F$12*IF(2027=sel_year,1,0) -> 0.8 | F69: =F$12*IF(2028=sel_year,1,0) -> 0 | G69: =F$12*IF(2029=sel_year,1,0) -> 0
B71: Freno legislativo | D71: 2026 | E71: 2027 | F71: 2028 | G71: 2029
B72: Δ crecimiento (pp) | D72: =G$6*D$33*(1-IF(sel_resp="Sí",G$14,0)) -> 0 | E72: =G$6*E$33*(1-IF(sel_resp="Sí",G$14,0)) -> -0.21 | F72: =G$6*F$33*(1-IF(sel_resp="Sí",G$14,0)) -> -0.21 | G72: =G$6*G$33*(1-IF(sel_resp="Sí",G$14,0)) -> 0
B73: Δ inflación (pp) | D73: =G$7*D$33 -> 0 | E73: =G$7*E$33 -> 0 | F73: =G$7*F$33 -> 0 | G73: =G$7*G$33 -> 0
B74: Δ saldo primario (pp PIB) | D74: =-(INDEX(Motor!$D$1:$D$600,5+(sel_idx-1)*72+8)+INDEX(Motor!$D$1:$D$600,5+(sel_idx-1)*72+9))*D$33-IF(sel_resp="Sí",G$15,0)*D$33 -> 0 | E74: =-(INDEX(Motor!$E$1:$E$600,5+(sel_idx-1)*72+8)+INDEX(Motor!$E$1:$E$600,5+(sel_idx-1)*72+9))*E$33-IF(sel_resp="Sí",G$15,0)*E$33 -> -0.345 | F74: =-(INDEX(Motor!$F$1:$F$600,5+(sel_idx-1)*72+8)+INDEX(Motor!$F$1:$F$600,5+(sel_idx-1)*72+9))*F$33-IF(sel_resp="Sí",G$15,0)*F$33 -> -0.52 | G74: =-(INDEX(Motor!$G$1:$G$600,5+(sel_idx-1)*72+8)+INDEX(Motor!$G$1:$G$600,5+(sel_idx-1)*72+9))*G$33-IF(sel_resp="Sí",G$15,0)*G$33 -> 0
B75: Δ RIN del año (US$ mn) | D75: =-G$20*IF(2026=sel_year,1,0)+G$20*IF(2026=sel_year+1,1,0) -> 0 | E75: =-G$20*IF(2027=sel_year,1,0)+G$20*IF(2027=sel_year+1,1,0) -> -1000 | F75: =-G$20*IF(2028=sel_year,1,0)+G$20*IF(2028=sel_year+1,1,0) -> 1000 | G75: =-G$20*IF(2029=sel_year,1,0)+G$20*IF(2029=sel_year+1,1,0) -> 0
B76: Δ crédito privado (pp) | D76: =G$10*D$33 -> 0 | E76: =G$10*E$33 -> 0 | F76: =G$10*F$33 -> 0 | G76: =G$10*G$33 -> 0
B77: Δ base monetaria (Bs mn) | D77: =G$11*D$33 -> 0 | E77: =G$11*E$33 -> 0 | F77: =G$11*F$33 -> 0 | G77: =G$11*G$33 -> 0
B78: Δ deuda por recapitalización (pp PIB) | D78: =G$12*D$33 -> 0 | E78: =G$12*E$33 -> 0 | F78: =G$12*F$33 -> 0 | G78: =G$12*G$33 -> 0
B80: Impacto aplicado (shock elegido) | D80: 2026 | E80: 2027 | F80: 2028 | G80: 2029
B81: Δ crecimiento (pp) | D81: =IF(shock_idx=1,D36,0)+IF(shock_idx=2,D45,0)+IF(shock_idx=3,D54,0)+IF(shock_idx=4,D63,0)+IF(shock_idx=5,D72,0) -> 0 | E81: =IF(shock_idx=1,E36,0)+IF(shock_idx=2,E45,0)+IF(shock_idx=3,E54,0)+IF(shock_idx=4,E63,0)+IF(shock_idx=5,E72,0) -> 0 | F81: =IF(shock_idx=1,F36,0)+IF(shock_idx=2,F45,0)+IF(shock_idx=3,F54,0)+IF(shock_idx=4,F63,0)+IF(shock_idx=5,F72,0) -> 0 | G81: =IF(shock_idx=1,G36,0)+IF(shock_idx=2,G45,0)+IF(shock_idx=3,G54,0)+IF(shock_idx=4,G63,0)+IF(shock_idx=5,G72,0) -> 0
B82: Δ inflación (pp) | D82: =IF(shock_idx=1,D37,0)+IF(shock_idx=2,D46,0)+IF(shock_idx=3,D55,0)+IF(shock_idx=4,D64,0)+IF(shock_idx=5,D73,0) -> 0 | E82: =IF(shock_idx=1,E37,0)+IF(shock_idx=2,E46,0)+IF(shock_idx=3,E55,0)+IF(shock_idx=4,E64,0)+IF(shock_idx=5,E73,0) -> 0 | F82: =IF(shock_idx=1,F37,0)+IF(shock_idx=2,F46,0)+IF(shock_idx=3,F55,0)+IF(shock_idx=4,F64,0)+IF(shock_idx=5,F73,0) -> 0 | G82: =IF(shock_idx=1,G37,0)+IF(shock_idx=2,G46,0)+IF(shock_idx=3,G55,0)+IF(shock_idx=4,G64,0)+IF(shock_idx=5,G73,0) -> 0
B83: Δ saldo primario (pp PIB) | D83: =IF(shock_idx=1,D38,0)+IF(shock_idx=2,D47,0)+IF(shock_idx=3,D56,0)+IF(shock_idx=4,D65,0)+IF(shock_idx=5,D74,0) -> 0 | E83: =IF(shock_idx=1,E38,0)+IF(shock_idx=2,E47,0)+IF(shock_idx=3,E56,0)+IF(shock_idx=4,E65,0)+IF(shock_idx=5,E74,0) -> 0 | F83: =IF(shock_idx=1,F38,0)+IF(shock_idx=2,F47,0)+IF(shock_idx=3,F56,0)+IF(shock_idx=4,F65,0)+IF(shock_idx=5,F74,0) -> 0 | G83: =IF(shock_idx=1,G38,0)+IF(shock_idx=2,G47,0)+IF(shock_idx=3,G56,0)+IF(shock_idx=4,G65,0)+IF(shock_idx=5,G74,0) -> 0
B84: Δ RIN del año (US$ mn) | D84: =IF(shock_idx=1,D39,0)+IF(shock_idx=2,D48,0)+IF(shock_idx=3,D57,0)+IF(shock_idx=4,D66,0)+IF(shock_idx=5,D75,0) -> 0 | E84: =IF(shock_idx=1,E39,0)+IF(shock_idx=2,E48,0)+IF(shock_idx=3,E57,0)+IF(shock_idx=4,E66,0)+IF(shock_idx=5,E75,0) -> 0 | F84: =IF(shock_idx=1,F39,0)+IF(shock_idx=2,F48,0)+IF(shock_idx=3,F57,0)+IF(shock_idx=4,F66,0)+IF(shock_idx=5,F75,0) -> 0 | G84: =IF(shock_idx=1,G39,0)+IF(shock_idx=2,G48,0)+IF(shock_idx=3,G57,0)+IF(shock_idx=4,G66,0)+IF(shock_idx=5,G75,0) -> 0
B85: Δ crédito privado (pp) | D85: =IF(shock_idx=1,D40,0)+IF(shock_idx=2,D49,0)+IF(shock_idx=3,D58,0)+IF(shock_idx=4,D67,0)+IF(shock_idx=5,D76,0) -> 0 | E85: =IF(shock_idx=1,E40,0)+IF(shock_idx=2,E49,0)+IF(shock_idx=3,E58,0)+IF(shock_idx=4,E67,0)+IF(shock_idx=5,E76,0) -> 0 | F85: =IF(shock_idx=1,F40,0)+IF(shock_idx=2,F49,0)+IF(shock_idx=3,F58,0)+IF(shock_idx=4,F67,0)+IF(shock_idx=5,F76,0) -> 0 | G85: =IF(shock_idx=1,G40,0)+IF(shock_idx=2,G49,0)+IF(shock_idx=3,G58,0)+IF(shock_idx=4,G67,0)+IF(shock_idx=5,G76,0) -> 0
B86: Δ base monetaria (Bs mn) | D86: =IF(shock_idx=1,D41,0)+IF(shock_idx=2,D50,0)+IF(shock_idx=3,D59,0)+IF(shock_idx=4,D68,0)+IF(shock_idx=5,D77,0) -> 0 | E86: =IF(shock_idx=1,E41,0)+IF(shock_idx=2,E50,0)+IF(shock_idx=3,E59,0)+IF(shock_idx=4,E68,0)+IF(shock_idx=5,E77,0) -> 0 | F86: =IF(shock_idx=1,F41,0)+IF(shock_idx=2,F50,0)+IF(shock_idx=3,F59,0)+IF(shock_idx=4,F68,0)+IF(shock_idx=5,F77,0) -> 0 | G86: =IF(shock_idx=1,G41,0)+IF(shock_idx=2,G50,0)+IF(shock_idx=3,G59,0)+IF(shock_idx=4,G68,0)+IF(shock_idx=5,G77,0) -> 0
B87: Δ deuda por recapitalización (pp PIB) | D87: =IF(shock_idx=1,D42,0)+IF(shock_idx=2,D51,0)+IF(shock_idx=3,D60,0)+IF(shock_idx=4,D69,0)+IF(shock_idx=5,D78,0) -> 0 | E87: =IF(shock_idx=1,E42,0)+IF(shock_idx=2,E51,0)+IF(shock_idx=3,E60,0)+IF(shock_idx=4,E69,0)+IF(shock_idx=5,E78,0) -> 0 | F87: =IF(shock_idx=1,F42,0)+IF(shock_idx=2,F51,0)+IF(shock_idx=3,F60,0)+IF(shock_idx=4,F69,0)+IF(shock_idx=5,F78,0) -> 0 | G87: =IF(shock_idx=1,G42,0)+IF(shock_idx=2,G51,0)+IF(shock_idx=3,G60,0)+IF(shock_idx=4,G69,0)+IF(shock_idx=5,G78,0) -> 0

Sheet Seleccionado
B2: Escenario seleccionado (+ shock) frente a la Base FMI
B3: Alimenta el Dashboard. Cambie la selección en el Dashboard.
B4: ="Escenario: "&sel_scen&" · Shock: "&sel_shock&IF(shock_idx>0," ("&sel_year&", respuesta: "&sel_resp&")","") -> Escenario: E6 Alternativo integrado · Shock: Ninguno
B6: Indicador | C6: FMI 2026 | D6: FMI 2027 | E6: FMI 2028 | F6: FMI 2029 | G6: Alt. 2026 | H6: Alt. 2027 | I6: Alt. 2028 | J6: Alt. 2029
B7: Crecimiento PIB real (%) | C7: =Motor!$D$29 -> -3 | D7: =Motor!$E$29 -> -1.5 | E7: =Motor!$F$29 -> 0.5 | F7: =Motor!$G$29 -> 2.5 | G7: =INDEX(Motor!$D$1:$D$600,5+(sel_idx-1)*72+24)+Shocks!D$81 -> -2.97175 | H7: =INDEX(Motor!$E$1:$E$600,5+(sel_idx-1)*72+24)+Shocks!E$81 -> -0.808 | I7: =INDEX(Motor!$F$1:$F$600,5+(sel_idx-1)*72+24)+Shocks!F$81 -> 1.059 | J7: =INDEX(Motor!$G$1:$G$600,5+(sel_idx-1)*72+24)+Shocks!G$81 -> 2.861
B8: Inflación promedio (%) | C8: =Motor!$D$48 -> 12.7 | D8: =Motor!$E$48 -> 15.8 | E8: =Motor!$F$48 -> 8.2 | F8: =Motor!$G$48 -> 7.3 | G8: =INDEX(Motor!$D$1:$D$600,5+(sel_idx-1)*72+43)+Shocks!D$82 -> 12.710562 | H8: =INDEX(Motor!$E$1:$E$600,5+(sel_idx-1)*72+43)+Shocks!E$82 -> 15.8265 | I8: =INDEX(Motor!$F$1:$F$600,5+(sel_idx-1)*72+43)+Shocks!F$82 -> 8.31375 | J8: =INDEX(Motor!$G$1:$G$600,5+(sel_idx-1)*72+43)+Shocks!G$82 -> 7.32725
B9: Inflación fin de período (%) | C9: =Motor!$D$49 -> 14.2 | D9: =Motor!$E$49 -> 10.7 | E9: =Motor!$F$49 -> 8.7 | F9: =Motor!$G$49 -> 6.2 | G9: =INDEX(Motor!$D$1:$D$600,5+(sel_idx-1)*72+44)+Shocks!D$82 -> 14.210562 | H9: =INDEX(Motor!$E$1:$E$600,5+(sel_idx-1)*72+44)+Shocks!E$82 -> 10.7265 | I9: =INDEX(Motor!$F$1:$F$600,5+(sel_idx-1)*72+44)+Shocks!F$82 -> 8.81375 | J9: =INDEX(Motor!$G$1:$G$600,5+(sel_idx-1)*72+44)+Shocks!G$82 -> 6.22725
B10: Saldo primario (% PIB) | C10: =Motor!$D$33 -> -6.5 | D10: =Motor!$E$33 -> -3 | E10: =Motor!$F$33 -> -0.3 | F10: =Motor!$G$33 -> 0.6 | G10: =INDEX(Motor!$D$1:$D$600,5+(sel_idx-1)*72+28)+Shocks!D$83+auto*Shocks!D$81 -> -6.47685 | H10: =INDEX(Motor!$E$1:$E$600,5+(sel_idx-1)*72+28)+Shocks!E$83+auto*Shocks!E$81 -> -2.8866 | I10: =INDEX(Motor!$F$1:$F$600,5+(sel_idx-1)*72+28)+Shocks!F$83+auto*Shocks!F$81 -> 0.4518 | J10: =INDEX(Motor!$G$1:$G$600,5+(sel_idx-1)*72+28)+Shocks!G$83+auto*Shocks!G$81 -> 1.6622
B11: Saldo primario (Bs mn) | C11: =Motor!$D$34 -> -32869 | D11: =Motor!$E$34 -> -17466 | E11: =Motor!$F$34 -> -1861.113 | F11: =Motor!$G$34 -> 4067.604 | G11: =INDEX(Motor!$D$1:$D$600,5+(sel_idx-1)*72+29)+(Shocks!D$83+auto*Shocks!D$81)/100*Datos_FMI!$F$9 -> -32751.77 | H11: =INDEX(Motor!$E$1:$E$600,5+(sel_idx-1)*72+29)+(Shocks!E$83+auto*Shocks!E$81)/100*Datos_FMI!$G$9 -> -16810.209 | I11: =INDEX(Motor!$F$1:$F$600,5+(sel_idx-1)*72+29)+(Shocks!F$83+auto*Shocks!F$81)/100*Datos_FMI!$H$9 -> 2802.8362 | J11: =INDEX(Motor!$G$1:$G$600,5+(sel_idx-1)*72+29)+(Shocks!G$83+auto*Shocks!G$81)/100*Datos_FMI!$I$9 -> 11268.619
B12: Saldo global (% PIB) | C12: =Motor!$D$37 -> -9.2 | D12: =Motor!$E$37 -> -6.7 | E12: =Motor!$F$37 -> -4 | F12: =Motor!$G$37 -> -3.2 | G12: =INDEX(Motor!$D$1:$D$600,5+(sel_idx-1)*72+32)+Shocks!D$83+auto*Shocks!D$81 -> -9.17685 | H12: =INDEX(Motor!$E$1:$E$600,5+(sel_idx-1)*72+32)+Shocks!E$83+auto*Shocks!E$81 -> -6.5852824 | I12: =INDEX(Motor!$F$1:$F$600,5+(sel_idx-1)*72+32)+Shocks!F$83+auto*Shocks!F$81 -> -3.2219738 | J12: =INDEX(Motor!$G$1:$G$600,5+(sel_idx-1)*72+32)+Shocks!G$83+auto*Shocks!G$81 -> -2.043951
B13: Deuda SPNF (% PIB) | C13: =Motor!$D$55 -> 100.47769 | D13: =Motor!$E$55 -> 95.361223 | E13: =Motor!$F$55 -> 93.185529 | F13: =Motor!$G$55 -> 89.203374 | G13: =INDEX(Motor!$D$1:$D$600,5+(sel_idx-1)*72+50)-(Shocks!D$83)-auto*(Shocks!D$81)+(Shocks!D$87) -> 100.41557 | H13: =INDEX(Motor!$E$1:$E$600,5+(sel_idx-1)*72+50)-(Shocks!D$83+Shocks!E$83)-auto*(Shocks!D$81+Shocks!E$81)+(Shocks!D$87+Shocks!E$87) -> 94.214638 | I13: =INDEX(Motor!$F$1:$F$600,5+(sel_idx-1)*72+50)-(Shocks!D$83+Shocks!E$83+Shocks!F$83)-auto*(Shocks!D$81+Shocks!E$81+Shocks!F$81)+(Shocks!D$87+Shocks!E$87+Shocks!F$87) -> 90.314434 | J13: =INDEX(Motor!$G$1:$G$600,5+(sel_idx-1)*72+50)-(Shocks!D$83+Shocks!E$83+Shocks!F$83+Shocks!G$83)-auto*(Shocks!D$81+Shocks!E$81+Shocks!F$81+Shocks!G$81)+(Shocks!D$87+Shocks!E$87+Shocks!F$87+Shocks!G$87) -> 84.846923
B14: RIN del programa (US$ mn) | C14: =Motor!$D$59 -> -581 | D14: =Motor!$E$59 -> 744 | E14: =Motor!$F$59 -> 1304 | F14: =Motor!$G$59 -> 1878 | G14: =INDEX(Motor!$D$1:$D$600,5+(sel_idx-1)*72+54)+(Shocks!D$84) -> -586.29349 | H14: =INDEX(Motor!$E$1:$E$600,5+(sel_idx-1)*72+54)+(Shocks!D$84+Shocks!E$84) -> 703.74912 | I14: =INDEX(Motor!$F$1:$F$600,5+(sel_idx-1)*72+54)+(Shocks!D$84+Shocks!E$84+Shocks!F$84) -> 1302.8827 | J14: =INDEX(Motor!$G$1:$G$600,5+(sel_idx-1)*72+54)+(Shocks!D$84+Shocks!E$84+Shocks!F$84+Shocks!G$84) -> 1800.8561
B15: RIB programa / ARA (%) | C15: =Motor!$D$61 -> 53.4 | D15: =Motor!$E$61 -> 86.1 | E15: =Motor!$F$61 -> 100.1 | F15: =Motor!$G$61 -> 112.3 | G15: =INDEX(Motor!$D$1:$D$600,5+(sel_idx-1)*72+56)*(1+(Shocks!D$84)/INDEX(Motor!$D$1:$D$600,5+(sel_idx-1)*72+55)) -> 53.284999 | H15: =INDEX(Motor!$E$1:$E$600,5+(sel_idx-1)*72+56)*(1+(Shocks!D$84+Shocks!E$84)/INDEX(Motor!$E$1:$E$600,5+(sel_idx-1)*72+55)) -> 85.229683 | I15: =INDEX(Motor!$F$1:$F$600,5+(sel_idx-1)*72+56)*(1+(Shocks!D$84+Shocks!E$84+Shocks!F$84)/INDEX(Motor!$F$1:$F$600,5+(sel_idx-1)*72+55)) -> 100.07615 | J15: =INDEX(Motor!$G$1:$G$600,5+(sel_idx-1)*72+56)*(1+(Shocks!D$84+Shocks!E$84+Shocks!F$84+Shocks!G$84)/INDEX(Motor!$G$1:$G$600,5+(sel_idx-1)*72+55)) -> 110.73256
B16: Crédito privado (variación %) | C16: =Motor!$D$63 -> 4 | D16: =Motor!$E$63 -> 7.3 | E16: =Motor!$F$63 -> 7.3 | F16: =Motor!$G$63 -> 9.5 | G16: =INDEX(Motor!$D$1:$D$600,5+(sel_idx-1)*72+58)+Shocks!D$85 -> 4.25 | H16: =INDEX(Motor!$E$1:$E$600,5+(sel_idx-1)*72+58)+Shocks!E$85 -> 10.55 | I16: =INDEX(Motor!$F$1:$F$600,5+(sel_idx-1)*72+58)+Shocks!F$85 -> 10.3 | J16: =INDEX(Motor!$G$1:$G$600,5+(sel_idx-1)*72+58)+Shocks!G$85 -> 11.5
B17: Base monetaria (Bs mn) | C17: =Motor!$D$66 -> 133900 | D17: =Motor!$E$66 -> 148333 | E17: =Motor!$F$66 -> 161304 | F17: =Motor!$G$66 -> 177013 | G17: =INDEX(Motor!$D$1:$D$600,5+(sel_idx-1)*72+61)+Shocks!D$86 -> 133900 | H17: =INDEX(Motor!$E$1:$E$600,5+(sel_idx-1)*72+61)+Shocks!E$86 -> 149074.67 | I17: =INDEX(Motor!$F$1:$F$600,5+(sel_idx-1)*72+61)+Shocks!F$86 -> 162110.52 | J17: =INDEX(Motor!$G$1:$G$600,5+(sel_idx-1)*72+61)+Shocks!G$86 -> 177898.07
B18: Crédito BCB requerido (Bs mn) | C18: =Motor!$D$42 -> 0 | D18: =Motor!$E$42 -> 0 | E18: =Motor!$F$42 -> 0 | F18: =Motor!$G$42 -> 0 | G18: =INDEX(Motor!$D$1:$D$600,5+(sel_idx-1)*72+37) -> 0 | H18: =INDEX(Motor!$E$1:$E$600,5+(sel_idx-1)*72+37) -> 0 | I18: =INDEX(Motor!$F$1:$F$600,5+(sel_idx-1)*72+37) -> 0 | J18: =INDEX(Motor!$G$1:$G$600,5+(sel_idx-1)*72+37) -> 0
B19: Asistencia social (Bs mn) | C19: =Motor!$D$68 -> 10890 | D19: =Motor!$E$68 -> 12722.578 | E19: =Motor!$F$68 -> 8064.823 | F19: =Motor!$G$68 -> 8813.142 | G19: =INDEX(Motor!$D$1:$D$600,5+(sel_idx-1)*72+63) -> 10890 | H19: =INDEX(Motor!$E$1:$E$600,5+(sel_idx-1)*72+63) -> 14168.326 | I19: =INDEX(Motor!$F$1:$F$600,5+(sel_idx-1)*72+63) -> 9305.565 | J19: =INDEX(Motor!$G$1:$G$600,5+(sel_idx-1)*72+63) -> 9830.043
B20: Δ Empleo vs FMI (miles) | C20: =Motor!$D$69 -> 0 | D20: =Motor!$E$69 -> 0 | E20: =Motor!$F$69 -> 0 | F20: =Motor!$G$69 -> 0 | G20: =INDEX(Motor!$D$1:$D$600,5+(sel_idx-1)*72+64)+emp_el*(Shocks!D$81)/100*pea -> 0.904 | H20: =INDEX(Motor!$E$1:$E$600,5+(sel_idx-1)*72+64)+emp_el*(Shocks!D$81+Shocks!E$81)/100*pea -> 23.048 | I20: =INDEX(Motor!$F$1:$F$600,5+(sel_idx-1)*72+64)+emp_el*(Shocks!D$81+Shocks!E$81+Shocks!F$81)/100*pea -> 40.936 | J20: =INDEX(Motor!$G$1:$G$600,5+(sel_idx-1)*72+64)+emp_el*(Shocks!D$81+Shocks!E$81+Shocks!F$81+Shocks!G$81)/100*pea -> 52.488
B21: Δ Pobreza vs FMI (pp) | C21: =Motor!$D$70 -> 0 | D21: =Motor!$E$70 -> 0 | E21: =Motor!$F$70 -> 0 | F21: =Motor!$G$70 -> 0 | G21: =INDEX(Motor!$D$1:$D$600,5+(sel_idx-1)*72+65)-pov_g*(Shocks!D$81)+pov_pi*Shocks!D$82 -> -0.018190625 | H21: =INDEX(Motor!$E$1:$E$600,5+(sel_idx-1)*72+65)-pov_g*(Shocks!D$81+Shocks!E$81)+pov_pi*Shocks!E$82 -> -1.0602 | I21: =INDEX(Motor!$F$1:$F$600,5+(sel_idx-1)*72+65)-pov_g*(Shocks!D$81+Shocks!E$81+Shocks!F$81)+pov_pi*Shocks!F$82 -> -1.2784125 | J21: =INDEX(Motor!$G$1:$G$600,5+(sel_idx-1)*72+65)-pov_g*(Shocks!D$81+Shocks!E$81+Shocks!F$81+Shocks!G$81)+pov_pi*Shocks!G$82 -> -1.4440875
B22: Δ Gini vs FMI (pts) | C22: =Motor!$D$71 -> 0 | D22: =Motor!$E$71 -> 0 | E22: =Motor!$F$71 -> 0 | F22: =Motor!$G$71 -> 0 | G22: =INDEX(Motor!$D$1:$D$600,5+(sel_idx-1)*72+66) -> 0 | H22: =INDEX(Motor!$E$1:$E$600,5+(sel_idx-1)*72+66) -> -0.145 | I22: =INDEX(Motor!$F$1:$F$600,5+(sel_idx-1)*72+66) -> -0.17 | J22: =INDEX(Motor!$G$1:$G$600,5+(sel_idx-1)*72+66) -> -0.18
B24: Metas a dic-2026 (seleccionado + shock) | C24: Valor | D24: Meta | E24: Holgura | F24: Estado
B25: Saldo primario (Bs mn) | C25: =G11 -> -32751.77 | D25: =meta_pb -> -33000 | E25: =C25-D25 -> 248.22952 | F25: =IF(ROUND(E25,0)>=0,"Cumple","No cumple") -> Cumple
B26: Variación RIN (US$ mn) | C26: =G14-Datos_FMI!$E$31 -> 2403.7065 | D26: =meta_nir -> 2400 | E26: =C26-D26 -> 3.706515 | F26: =IF(ROUND(E26,0)>=0,"Cumple","No cumple") -> Cumple
B27: Crédito BCB al sector público (Bs mn) | C27: =G18 -> 0 | D27: =meta_bcb -> 0 | E27: =D27-C27 -> 0 | F27: =IF(ROUND(E27,0)>=0,"Cumple","No cumple") -> Cumple
B28: Asistencia social (Bs mn) | C28: =G19 -> 10890 | D28: =meta_soc -> 9300 | E28: =C28-D28 -> 1590 | F28: =IF(ROUND(E28,0)>=0,"Cumple","No cumple") -> Cumple
B29: Base monetaria (Bs mn) | C29: =G17 -> 133900 | D29: =meta_bm -> 133900 | E29: =D29-C29 -> 0 | F29: =IF(ROUND(E29,0)>=0,"Cumple","No cumple") -> Cumple

Sheet Evaluacion
B2: Evaluación de escenarios: metas 2026 e índice de eficiencia
B3: Sin shocks. Índice 0–100: normalización mín–máx entre escenarios, ponderada (pesos editables).
B5: Indicador | C5: Base FMI | D5: E1 Fiscal gradual | E5: E2 Monetaria-crédito | F5: E3 Banda cambiaria | G5: E4 Tributaria progresiva | H5: E5 Protección social | I5: E6 Alternativo integrado | J5: Meta / peso
B6: Saldo primario 2026 (Bs mn) | C6: =Motor!$D$34 -> -32869 | D6: =Motor!$D$106 -> -33413.37 | E6: =Motor!$D$178 -> -32838.617 | F6: =Motor!$D$250 -> -32884.192 | G6: =Motor!$D$322 -> -32695.308 | H6: =Motor!$D$394 -> -32858.872 | I6: =Motor!$D$466 -> -32751.77 | J6: =meta_pb -> -33000
B7: Variación RIN 2026 (US$ mn) | C7: =Motor!$D$59-Datos_FMI!$E$31 -> 2409 | D7: =Motor!$D$131-Datos_FMI!$E$31 -> 2492.6042 | E7: =Motor!$D$203-Datos_FMI!$E$31 -> 2403.3786 | F7: =Motor!$D$275-Datos_FMI!$E$31 -> 2261.8107 | G7: =Motor!$D$347-Datos_FMI!$E$31 -> 2409.6558 | H7: =Motor!$D$419-Datos_FMI!$E$31 -> 2407.1262 | I7: =Motor!$D$491-Datos_FMI!$E$31 -> 2403.7065 | J7: =meta_nir -> 2400
B8: Crédito BCB al sector público 2026 (Bs mn) | C8: =Motor!$D$42 -> 0 | D8: =Motor!$D$114 -> 0 | E8: =Motor!$D$186 -> 0 | F8: =Motor!$D$258 -> 0 | G8: =Motor!$D$330 -> 0 | H8: =Motor!$D$402 -> 0 | I8: =Motor!$D$474 -> 0 | J8: =meta_bcb -> 0
B9: Asistencia social 2026 (Bs mn) | C9: =Motor!$D$68 -> 10890 | D9: =Motor!$D$140 -> 10890 | E9: =Motor!$D$212 -> 10890 | F9: =Motor!$D$284 -> 10890 | G9: =Motor!$D$356 -> 10890 | H9: =Motor!$D$428 -> 11143.195 | I9: =Motor!$D$500 -> 10890 | J9: =meta_soc -> 9300
B10: Base monetaria dic-2026 (Bs mn) | C10: =Motor!$D$66 -> 133900 | D10: =Motor!$D$138 -> 133900 | E10: =Motor!$D$210 -> 133900 | F10: =Motor!$D$282 -> 133900 | G10: =Motor!$D$354 -> 133900 | H10: =Motor!$D$426 -> 133900 | I10: =Motor!$D$498 -> 133900 | J10: =meta_bm -> 133900
B11: ✔ Meta saldo primario | C11: =IF(ROUND(C6,0)>=meta_pb,"Cumple","No cumple") -> Cumple | D11: =IF(ROUND(D6,0)>=meta_pb,"Cumple","No cumple") -> No cumple | E11: =IF(ROUND(E6,0)>=meta_pb,"Cumple","No cumple") -> Cumple | F11: =IF(ROUND(F6,0)>=meta_pb,"Cumple","No cumple") -> Cumple | G11: =IF(ROUND(G6,0)>=meta_pb,"Cumple","No cumple") -> Cumple | H11: =IF(ROUND(H6,0)>=meta_pb,"Cumple","No cumple") -> Cumple | I11: =IF(ROUND(I6,0)>=meta_pb,"Cumple","No cumple") -> Cumple
B12: ✔ Meta RIN | C12: =IF(ROUND(C7,0)>=meta_nir,"Cumple","No cumple") -> Cumple | D12: =IF(ROUND(D7,0)>=meta_nir,"Cumple","No cumple") -> Cumple | E12: =IF(ROUND(E7,0)>=meta_nir,"Cumple","No cumple") -> Cumple | F12: =IF(ROUND(F7,0)>=meta_nir,"Cumple","No cumple") -> No cumple | G12: =IF(ROUND(G7,0)>=meta_nir,"Cumple","No cumple") -> Cumple | H12: =IF(ROUND(H7,0)>=meta_nir,"Cumple","No cumple") -> Cumple | I12: =IF(ROUND(I7,0)>=meta_nir,"Cumple","No cumple") -> Cumple
B13: ✔ Meta crédito BCB = 0 | C13: =IF(ROUND(C8,0)<=meta_bcb,"Cumple","No cumple") -> Cumple | D13: =IF(ROUND(D8,0)<=meta_bcb,"Cumple","No cumple") -> Cumple | E13: =IF(ROUND(E8,0)<=meta_bcb,"Cumple","No cumple") -> Cumple | F13: =IF(ROUND(F8,0)<=meta_bcb,"Cumple","No cumple") -> Cumple | G13: =IF(ROUND(G8,0)<=meta_bcb,"Cumple","No cumple") -> Cumple | H13: =IF(ROUND(H8,0)<=meta_bcb,"Cumple","No cumple") -> Cumple | I13: =IF(ROUND(I8,0)<=meta_bcb,"Cumple","No cumple") -> Cumple
B14: ✔ Meta asistencia social | C14: =IF(ROUND(C9,0)>=meta_soc,"Cumple","No cumple") -> Cumple | D14: =IF(ROUND(D9,0)>=meta_soc,"Cumple","No cumple") -> Cumple | E14: =IF(ROUND(E9,0)>=meta_soc,"Cumple","No cumple") -> Cumple | F14: =IF(ROUND(F9,0)>=meta_soc,"Cumple","No cumple") -> Cumple | G14: =IF(ROUND(G9,0)>=meta_soc,"Cumple","No cumple") -> Cumple | H14: =IF(ROUND(H9,0)>=meta_soc,"Cumple","No cumple") -> Cumple | I14: =IF(ROUND(I9,0)>=meta_soc,"Cumple","No cumple") -> Cumple
B15: ✔ Meta base monetaria | C15: =IF(ROUND(C10,0)<=meta_bm,"Cumple","No cumple") -> Cumple | D15: =IF(ROUND(D10,0)<=meta_bm,"Cumple","No cumple") -> Cumple | E15: =IF(ROUND(E10,0)<=meta_bm,"Cumple","No cumple") -> Cumple | F15: =IF(ROUND(F10,0)<=meta_bm,"Cumple","No cumple") -> Cumple | G15: =IF(ROUND(G10,0)<=meta_bm,"Cumple","No cumple") -> Cumple | H15: =IF(ROUND(H10,0)<=meta_bm,"Cumple","No cumple") -> Cumple | I15: =IF(ROUND(I10,0)<=meta_bm,"Cumple","No cumple") -> Cumple
B16: Metas 2026 cumplidas (de 5) | C16: =COUNTIF(C11:C15,"Cumple") -> 5 | D16: =COUNTIF(D11:D15,"Cumple") -> 4 | E16: =COUNTIF(E11:E15,"Cumple") -> 5 | F16: =COUNTIF(F11:F15,"Cumple") -> 4 | G16: =COUNTIF(G11:G15,"Cumple") -> 5 | H16: =COUNTIF(H11:H15,"Cumple") -> 5 | I16: =COUNTIF(I11:I15,"Cumple") -> 5
B17: Crédito BCB requerido 2026–2029 (Bs mn) | C17: =SUM(Motor!$D$42:$G$42) -> 0 | D17: =SUM(Motor!$D$114:$G$114) -> 0 | E17: =SUM(Motor!$D$186:$G$186) -> 0 | F17: =SUM(Motor!$D$258:$G$258) -> 0 | G17: =SUM(Motor!$D$330:$G$330) -> 0 | H17: =SUM(Motor!$D$402:$G$402) -> 0 | I17: =SUM(Motor!$D$474:$G$474) -> 0
B18: Crecimiento real acumulado 2026–2029 (%) | C18: =((1+Motor!$D$29/100)*(1+Motor!$E$29/100)*(1+Motor!$F$29/100)*(1+Motor!$G$29/100)-1)*100 -> -1.5767069 | D18: =((1+Motor!$D$101/100)*(1+Motor!$E$101/100)*(1+Motor!$F$101/100)*(1+Motor!$G$101/100)-1)*100 -> 0.17629456 | E18: =((1+Motor!$D$173/100)*(1+Motor!$E$173/100)*(1+Motor!$F$173/100)*(1+Motor!$G$173/100)-1)*100 -> -0.065671377 | F18: =((1+Motor!$D$245/100)*(1+Motor!$E$245/100)*(1+Motor!$F$245/100)*(1+Motor!$G$245/100)-1)*100 -> -1.8013202 | G18: =((1+Motor!$D$317/100)*(1+Motor!$E$317/100)*(1+Motor!$F$317/100)*(1+Motor!$G$317/100)-1)*100 -> -2.2080605 | H18: =((1+Motor!$D$389/100)*(1+Motor!$E$389/100)*(1+Motor!$F$389/100)*(1+Motor!$G$389/100)-1)*100 -> -1.3167587 | I18: =((1+Motor!$D$461/100)*(1+Motor!$E$461/100)*(1+Motor!$F$461/100)*(1+Motor!$G$461/100)-1)*100 -> 0.046196877
B19: Inflación promedio 2026–2029 (%) | C19: =AVERAGE(Motor!$D$48:$G$48) -> 11 | D19: =AVERAGE(Motor!$D$120:$G$120) -> 11.110938 | E19: =AVERAGE(Motor!$D$192:$G$192) -> 11.676875 | F19: =AVERAGE(Motor!$D$264:$G$264) -> 10.329555 | G19: =AVERAGE(Motor!$D$336:$G$336) -> 11.041781 | H19: =AVERAGE(Motor!$D$408:$G$408) -> 11.016394 | I19: =AVERAGE(Motor!$D$480:$G$480) -> 11.044516
B20: Saldo primario 2029 (% PIB) | C20: =Motor!$G$33 -> 0.6 | D20: =Motor!$G$105 -> 0.2085 | E20: =Motor!$G$177 -> 0.678 | F20: =Motor!$G$249 -> 0.594 | G20: =Motor!$G$321 -> 2.0347 | H20: =Motor!$G$393 -> 0.60490787 | I20: =Motor!$G$465 -> 1.6622
B21: Deuda SPNF 2029 (% PIB) | C21: =Motor!$G$55 -> 89.203374 | D21: =Motor!$G$127 -> 89.229857 | E21: =Motor!$G$199 -> 85.830045 | F21: =Motor!$G$271 -> 88.799442 | G21: =Motor!$G$343 -> 86.134624 | H21: =Motor!$G$415 -> 89.923874 | I21: =Motor!$G$487 -> 84.846923
B22: RIN programa 2029 (US$ mn) | C22: =Motor!$G$59 -> 1878 | D22: =Motor!$G$131 -> 2727.2943 | E22: =Motor!$G$203 -> 1397.2205 | F22: =Motor!$G$275 -> 771.74304 | G22: =Motor!$G$347 -> 2007.4171 | H22: =Motor!$G$419 -> 1980.4677 | I22: =Motor!$G$491 -> 1800.8561
B23: RIB / ARA 2029 (%) | C23: =Motor!$G$61 -> 112.3 | D23: =Motor!$G$133 -> 129.55633 | E23: =Motor!$G$205 -> 102.53131 | F23: =Motor!$G$277 -> 89.822588 | G23: =Motor!$G$349 -> 114.92955 | H23: =Motor!$G$421 -> 114.38198 | I23: =Motor!$G$493 -> 110.73256
B24: Crédito privado promedio 2027–2029 (%) | C24: =AVERAGE(Motor!$E$63:$G$63) -> 8.0333333 | D24: =AVERAGE(Motor!$E$135:$G$135) -> 8.0333333 | E24: =AVERAGE(Motor!$E$207:$G$207) -> 12.2 | F24: =AVERAGE(Motor!$E$279:$G$279) -> 8.0274597 | G24: =AVERAGE(Motor!$E$351:$G$351) -> 8.0333333 | H24: =AVERAGE(Motor!$E$423:$G$423) -> 7.8730702 | I24: =AVERAGE(Motor!$E$495:$G$495) -> 10.783333
B25: Asistencia social acumulada 2026–2029 (Bs mn) | C25: =SUM(Motor!$D$68:$G$68) -> 40490.543 | D25: =SUM(Motor!$D$140:$G$140) -> 40490.543 | E25: =SUM(Motor!$D$212:$G$212) -> 40490.543 | F25: =SUM(Motor!$D$284:$G$284) -> 40490.543 | G25: =SUM(Motor!$D$356:$G$356) -> 40490.543 | H25: =SUM(Motor!$D$428:$G$428) -> 46273.916 | I25: =SUM(Motor!$D$500:$G$500) -> 44193.933
B26: Δ Empleo 2029 vs FMI (miles) | C26: =Motor!$G$69 -> 0 | D26: =Motor!$G$141 -> 56.8 | E26: =Motor!$G$213 -> 48.96 | F26: =Motor!$G$285 -> -7.2676645 | G26: =Motor!$G$357 -> -20.72 | H26: =Motor!$G$429 -> 8.3937691 | I26: =Motor!$G$501 -> 52.488
B27: Δ Pobreza 2029 vs FMI (pp) | C27: =Motor!$G$70 -> 0 | D27: =Motor!$G$142 -> -1.2221563 | E27: =Motor!$G$214 -> -0.99825 | F27: =Motor!$G$286 -> 0.10535516 | G27: =Motor!$G$358 -> 0.46481875 | H27: =Motor!$G$430 -> -0.52869348 | I27: =Motor!$G$502 -> -1.4440875
B28: Δ Gini 2029 vs FMI (pts) | C28: =Motor!$G$71 -> 0 | D28: =Motor!$G$143 -> 0 | E28: =Motor!$G$215 -> 0 | F28: =Motor!$G$287 -> 0 | G28: =Motor!$G$359 -> -0.18 | H28: =Motor!$G$431 -> -0.08 | I28: =Motor!$G$503 -> -0.18
B30: Índice de eficiencia (0–100) | J30: Peso | K30: Dirección
B31: Cumplimiento de metas 2026 | C31: =IF(MAX($C$16:$I$16)=MIN($C$16:$I$16),0.5,(C$16-MIN($C$16:$I$16))/(MAX($C$16:$I$16)-MIN($C$16:$I$16))) -> 1 | D31: =IF(MAX($C$16:$I$16)=MIN($C$16:$I$16),0.5,(D$16-MIN($C$16:$I$16))/(MAX($C$16:$I$16)-MIN($C$16:$I$16))) -> 0 | E31: =IF(MAX($C$16:$I$16)=MIN($C$16:$I$16),0.5,(E$16-MIN($C$16:$I$16))/(MAX($C$16:$I$16)-MIN($C$16:$I$16))) -> 1 | F31: =IF(MAX($C$16:$I$16)=MIN($C$16:$I$16),0.5,(F$16-MIN($C$16:$I$16))/(MAX($C$16:$I$16)-MIN($C$16:$I$16))) -> 0 | G31: =IF(MAX($C$16:$I$16)=MIN($C$16:$I$16),0.5,(G$16-MIN($C$16:$I$16))/(MAX($C$16:$I$16)-MIN($C$16:$I$16))) -> 1 | H31: =IF(MAX($C$16:$I$16)=MIN($C$16:$I$16),0.5,(H$16-MIN($C$16:$I$16))/(MAX($C$16:$I$16)-MIN($C$16:$I$16))) -> 1 | I31: =IF(MAX($C$16:$I$16)=MIN($C$16:$I$16),0.5,(I$16-MIN($C$16:$I$16))/(MAX($C$16:$I$16)-MIN($C$16:$I$16))) -> 1 | J31: 0.25 | K31: Mayor = mejor
B32: Crecimiento acumulado | C32: =IF(MAX($C$18:$I$18)=MIN($C$18:$I$18),0.5,(C$18-MIN($C$18:$I$18))/(MAX($C$18:$I$18)-MIN($C$18:$I$18))) -> 0.26479011 | D32: =IF(MAX($C$18:$I$18)=MIN($C$18:$I$18),0.5,(D$18-MIN($C$18:$I$18))/(MAX($C$18:$I$18)-MIN($C$18:$I$18))) -> 1 | E32: =IF(MAX($C$18:$I$18)=MIN($C$18:$I$18),0.5,(E$18-MIN($C$18:$I$18))/(MAX($C$18:$I$18)-MIN($C$18:$I$18))) -> 0.89851934 | F32: =IF(MAX($C$18:$I$18)=MIN($C$18:$I$18),0.5,(F$18-MIN($C$18:$I$18))/(MAX($C$18:$I$18)-MIN($C$18:$I$18))) -> 0.17058714 | G32: =IF(MAX($C$18:$I$18)=MIN($C$18:$I$18),0.5,(G$18-MIN($C$18:$I$18))/(MAX($C$18:$I$18)-MIN($C$18:$I$18))) -> 0 | H32: =IF(MAX($C$18:$I$18)=MIN($C$18:$I$18),0.5,(H$18-MIN($C$18:$I$18))/(MAX($C$18:$I$18)-MIN($C$18:$I$18))) -> 0.37381252 | I32: =IF(MAX($C$18:$I$18)=MIN($C$18:$I$18),0.5,(I$18-MIN($C$18:$I$18))/(MAX($C$18:$I$18)-MIN($C$18:$I$18))) -> 0.94543695 | J32: 0.2 | K32: Mayor = mejor
B33: Inflación promedio | C33: =IF(MAX($C$19:$I$19)=MIN($C$19:$I$19),0.5,(MAX($C$19:$I$19)-C$19)/(MAX($C$19:$I$19)-MIN($C$19:$I$19))) -> 0.50238635 | D33: =IF(MAX($C$19:$I$19)=MIN($C$19:$I$19),0.5,(MAX($C$19:$I$19)-D$19)/(MAX($C$19:$I$19)-MIN($C$19:$I$19))) -> 0.42004694 | E33: =IF(MAX($C$19:$I$19)=MIN($C$19:$I$19),0.5,(MAX($C$19:$I$19)-E$19)/(MAX($C$19:$I$19)-MIN($C$19:$I$19))) -> 0 | F33: =IF(MAX($C$19:$I$19)=MIN($C$19:$I$19),0.5,(MAX($C$19:$I$19)-F$19)/(MAX($C$19:$I$19)-MIN($C$19:$I$19))) -> 1 | G33: =IF(MAX($C$19:$I$19)=MIN($C$19:$I$19),0.5,(MAX($C$19:$I$19)-G$19)/(MAX($C$19:$I$19)-MIN($C$19:$I$19))) -> 0.4713757 | H33: =IF(MAX($C$19:$I$19)=MIN($C$19:$I$19),0.5,(MAX($C$19:$I$19)-H$19)/(MAX($C$19:$I$19)-MIN($C$19:$I$19))) -> 0.49021842 | I33: =IF(MAX($C$19:$I$19)=MIN($C$19:$I$19),0.5,(MAX($C$19:$I$19)-I$19)/(MAX($C$19:$I$19)-MIN($C$19:$I$19))) -> 0.46934621 | J33: 0.15 | K33: Menor = mejor
B34: Deuda 2029 | C34: =IF(MAX($C$21:$I$21)=MIN($C$21:$I$21),0.5,(MAX($C$21:$I$21)-C$21)/(MAX($C$21:$I$21)-MIN($C$21:$I$21))) -> 0.14191597 | D34: =IF(MAX($C$21:$I$21)=MIN($C$21:$I$21),0.5,(MAX($C$21:$I$21)-D$21)/(MAX($C$21:$I$21)-MIN($C$21:$I$21))) -> 0.13669969 | E34: =IF(MAX($C$21:$I$21)=MIN($C$21:$I$21),0.5,(MAX($C$21:$I$21)-E$21)/(MAX($C$21:$I$21)-MIN($C$21:$I$21))) -> 0.80635586 | F34: =IF(MAX($C$21:$I$21)=MIN($C$21:$I$21),0.5,(MAX($C$21:$I$21)-F$21)/(MAX($C$21:$I$21)-MIN($C$21:$I$21))) -> 0.22147776 | G34: =IF(MAX($C$21:$I$21)=MIN($C$21:$I$21),0.5,(MAX($C$21:$I$21)-G$21)/(MAX($C$21:$I$21)-MIN($C$21:$I$21))) -> 0.74636322 | H34: =IF(MAX($C$21:$I$21)=MIN($C$21:$I$21),0.5,(MAX($C$21:$I$21)-H$21)/(MAX($C$21:$I$21)-MIN($C$21:$I$21))) -> 0 | I34: =IF(MAX($C$21:$I$21)=MIN($C$21:$I$21),0.5,(MAX($C$21:$I$21)-I$21)/(MAX($C$21:$I$21)-MIN($C$21:$I$21))) -> 1 | J34: 0.15 | K34: Menor = mejor
B35: RIN 2029 | C35: =IF(MAX($C$22:$I$22)=MIN($C$22:$I$22),0.5,(C$22-MIN($C$22:$I$22))/(MAX($C$22:$I$22)-MIN($C$22:$I$22))) -> 0.56570081 | D35: =IF(MAX($C$22:$I$22)=MIN($C$22:$I$22),0.5,(D$22-MIN($C$22:$I$22))/(MAX($C$22:$I$22)-MIN($C$22:$I$22))) -> 1 | E35: =IF(MAX($C$22:$I$22)=MIN($C$22:$I$22),0.5,(E$22-MIN($C$22:$I$22))/(MAX($C$22:$I$22)-MIN($C$22:$I$22))) -> 0.3198471 | F35: =IF(MAX($C$22:$I$22)=MIN($C$22:$I$22),0.5,(F$22-MIN($C$22:$I$22))/(MAX($C$22:$I$22)-MIN($C$22:$I$22))) -> 0 | G35: =IF(MAX($C$22:$I$22)=MIN($C$22:$I$22),0.5,(G$22-MIN($C$22:$I$22))/(MAX($C$22:$I$22)-MIN($C$22:$I$22))) -> 0.63188014 | H35: =IF(MAX($C$22:$I$22)=MIN($C$22:$I$22),0.5,(H$22-MIN($C$22:$I$22))/(MAX($C$22:$I$22)-MIN($C$22:$I$22))) -> 0.61809916 | I35: =IF(MAX($C$22:$I$22)=MIN($C$22:$I$22),0.5,(I$22-MIN($C$22:$I$22))/(MAX($C$22:$I$22)-MIN($C$22:$I$22))) -> 0.52625212 | J35: 0.1 | K35: Mayor = mejor
B36: Pobreza 2029 | C36: =IF(MAX($C$27:$I$27)=MIN($C$27:$I$27),0.5,(MAX($C$27:$I$27)-C$27)/(MAX($C$27:$I$27)-MIN($C$27:$I$27))) -> 0.24350004 | D36: =IF(MAX($C$27:$I$27)=MIN($C$27:$I$27),0.5,(MAX($C$27:$I$27)-D$27)/(MAX($C$27:$I$27)-MIN($C$27:$I$27))) -> 0.88373905 | E36: =IF(MAX($C$27:$I$27)=MIN($C$27:$I$27),0.5,(MAX($C$27:$I$27)-E$27)/(MAX($C$27:$I$27)-MIN($C$27:$I$27))) -> 0.76644348 | F36: =IF(MAX($C$27:$I$27)=MIN($C$27:$I$27),0.5,(MAX($C$27:$I$27)-F$27)/(MAX($C$27:$I$27)-MIN($C$27:$I$27))) -> 0.18830867 | G36: =IF(MAX($C$27:$I$27)=MIN($C$27:$I$27),0.5,(MAX($C$27:$I$27)-G$27)/(MAX($C$27:$I$27)-MIN($C$27:$I$27))) -> 0 | H36: =IF(MAX($C$27:$I$27)=MIN($C$27:$I$27),0.5,(MAX($C$27:$I$27)-H$27)/(MAX($C$27:$I$27)-MIN($C$27:$I$27))) -> 0.52046151 | I36: =IF(MAX($C$27:$I$27)=MIN($C$27:$I$27),0.5,(MAX($C$27:$I$27)-I$27)/(MAX($C$27:$I$27)-MIN($C$27:$I$27))) -> 1 | J36: 0.1 | K36: Menor = mejor
B37: Empleo 2029 | C37: =IF(MAX($C$26:$I$26)=MIN($C$26:$I$26),0.5,(C$26-MIN($C$26:$I$26))/(MAX($C$26:$I$26)-MIN($C$26:$I$26))) -> 0.26728586 | D37: =IF(MAX($C$26:$I$26)=MIN($C$26:$I$26),0.5,(D$26-MIN($C$26:$I$26))/(MAX($C$26:$I$26)-MIN($C$26:$I$26))) -> 1 | E37: =IF(MAX($C$26:$I$26)=MIN($C$26:$I$26),0.5,(E$26-MIN($C$26:$I$26))/(MAX($C$26:$I$26)-MIN($C$26:$I$26))) -> 0.89886481 | F37: =IF(MAX($C$26:$I$26)=MIN($C$26:$I$26),0.5,(F$26-MIN($C$26:$I$26))/(MAX($C$26:$I$26)-MIN($C$26:$I$26))) -> 0.17353374 | G37: =IF(MAX($C$26:$I$26)=MIN($C$26:$I$26),0.5,(G$26-MIN($C$26:$I$26))/(MAX($C$26:$I$26)-MIN($C$26:$I$26))) -> 0 | H37: =IF(MAX($C$26:$I$26)=MIN($C$26:$I$26),0.5,(H$26-MIN($C$26:$I$26))/(MAX($C$26:$I$26)-MIN($C$26:$I$26))) -> 0.37556462 | I37: =IF(MAX($C$26:$I$26)=MIN($C$26:$I$26),0.5,(I$26-MIN($C$26:$I$26))/(MAX($C$26:$I$26)-MIN($C$26:$I$26))) -> 0.94437564 | J37: 0.05 | K37: Mayor = mejor
B38: ÍNDICE DE EFICIENCIA | C38: =100*SUMPRODUCT(C31:C37,$J$31:$J$37)/SUM($J$31:$J$37) -> 49.388775 | D38: =100*SUMPRODUCT(D31:D37,$J$31:$J$37)/SUM($J$31:$J$37) -> 52.18859 | E38: =100*SUMPRODUCT(E31:E37,$J$31:$J$37)/SUM($J$31:$J$37) -> 70.422955 | F38: =100*SUMPRODUCT(F31:F37,$J$31:$J$37)/SUM($J$31:$J$37) -> 24.484664 | G38: =100*SUMPRODUCT(G31:G37,$J$31:$J$37)/SUM($J$31:$J$37) -> 49.584885 | H38: =100*SUMPRODUCT(H31:H37,$J$31:$J$37)/SUM($J$31:$J$37) -> 53.092957 | I38: =100*SUMPRODUCT(I31:I37,$J$31:$J$37)/SUM($J$31:$J$37) -> 85.933332 | J38: =SUM(J31:J37) -> 1
B39: Ranking | C39: =RANK(C38,$C$38:$I$38) -> 6 | D39: =RANK(D38,$C$38:$I$38) -> 4 | E39: =RANK(E38,$C$38:$I$38) -> 2 | F39: =RANK(F38,$C$38:$I$38) -> 7 | G39: =RANK(G38,$C$38:$I$38) -> 5 | H39: =RANK(H38,$C$38:$I$38) -> 3 | I39: =RANK(I38,$C$38:$I$38) -> 1

Sheet Contrafactual
B2: El presupuesto contrafactual (misión 3)
B3: FMI vs escenario seleccionado en el Dashboard (+ shock si se eligió). Las justificaciones se refieren al escenario E6; ajústelas si defiende otro.
B5: Variable | C5: FMI 2026 | D5: FMI 2027 | E5: FMI 2029 | F5: Alt. 2026 | G5: Alt. 2027 | H5: Alt. 2029 | I5: Justificación (canal de transmisión)
B6: Saldo global (% PIB) | C6: =Seleccionado!C12 -> -9.2 | D6: =Seleccionado!D12 -> -6.7 | E6: =Seleccionado!F12 -> -3.2 | F6: =Seleccionado!G12 -> -9.17685 | G6: =Seleccionado!H12 -> -6.5852824 | H6: =Seleccionado!J12 -> -2.043951 | I6: ¿Qué gastos o ingresos cambian? Desde 2027: +0,6 pp inversión productiva financiada en parte por recorte de gasto corriente (−0,4/−0,5 pp: reestructuración de EP no viables, compras) y reforma tributaria adelantada (anti-evasión IVA, renta personal/patrimonio, revisión de exenciones con realización 60–85%). 2026 no se toca para cumplir el piso de −Bs 33.000 mn.
B7: Inflación promedio (%) | C7: =Seleccionado!C8 -> 12.7 | D7: =Seleccionado!D8 -> 15.8 | E7: =Seleccionado!F8 -> 7.3 | F7: =Seleccionado!G8 -> 12.710562 | G7: =Seleccionado!H8 -> 15.8265 | H7: =Seleccionado!J8 -> 7.32725 | I7: ¿Qué mecanismos? Subsidio diésel productivo focalizado transitorio en 2027 (−traspaso a transporte/alimentos), suavizado cambiario con reglas (−1 pp depreciación × traspaso 0,35) compensan la base monetaria algo mayor (+0,5 pp) y la presión de demanda.
B8: RIN del programa (US$ mn) | C8: =Seleccionado!C14 -> -581 | D8: =Seleccionado!D14 -> 744 | E8: =Seleccionado!F14 -> 1878 | F8: =Seleccionado!G14 -> -586.29349 | G8: =Seleccionado!H14 -> 703.74912 | H8: =Seleccionado!J14 -> 1800.8561 | I8: ¿De dónde provienen las divisas? CAF/BID adicionales (US$ 700 mn 2027–29), menos ventas de divisas acotadas por regla (US$ 400 mn en 2027–29) e importaciones inducidas por más crecimiento (elasticidad 1,5).
B9: Crecimiento PIB real (%) | C9: =Seleccionado!C7 -> -3 | D9: =Seleccionado!D7 -> -1.5 | E9: =Seleccionado!F7 -> 2.5 | F9: =Seleccionado!G7 -> -2.97175 | G9: =Seleccionado!H7 -> -0.808 | H9: =Seleccionado!J7 -> 2.861 | I9: ¿Cómo cambian consumo e inversión? Inversión pública con multiplicador 0,7 y efecto oferta; transferencias focalizadas (0,6); crédito productivo (+3 pp, elasticidad 0,12). Restan: impuestos progresivos (0,15) y recorte corriente (0,4).
B10: Asistencia social (Bs mn) | C10: =Seleccionado!C19 -> 10890 | D10: =Seleccionado!D19 -> 12722.578 | E10: =Seleccionado!F19 -> 8813.142 | F10: =Seleccionado!G19 -> 10890 | G10: =Seleccionado!H19 -> 14168.326 | H10: =Seleccionado!J19 -> 9830.043 | I10: ¿Quién recibe la protección? Hogares del registro PEPE (84% de los pobres) y adultos mayores no pensionistas; +0,25 pp PIB en 2027 mientras se retira el subsidio y se construye el registro social unificado (SB mar-2027).
B11: Crédito productivo (var. %) | C11: =Seleccionado!C16 -> 4 | D11: =Seleccionado!D16 -> 7.3 | E11: =Seleccionado!F16 -> 9.5 | F11: =Seleccionado!G16 -> 4.25 | G11: =Seleccionado!H16 -> 10.55 | H11: =Seleccionado!J16 -> 11.5 | I11: ¿Qué ocurre con tasas y disponibilidad? Encaje diferenciado para cartera productiva y fondos de garantía (FOGACP) sin topes de tasas; neutral en base monetaria; parte se compensa por desplazamiento del financiamiento interno del Estado.
B12: Deuda SPNF (% PIB) | C12: =Seleccionado!C13 -> 100.47769 | D12: =Seleccionado!D13 -> 95.361223 | E12: =Seleccionado!F13 -> 89.203374 | F12: =Seleccionado!G13 -> 100.41557 | G12: =Seleccionado!H13 -> 94.214638 | H12: =Seleccionado!J13 -> 84.846923 | I12: Sostenibilidad: el mayor crecimiento nominal y la recaudación adelantada compensan el gasto en inversión; se exige que la deuda 2029 no supere la senda FMI.
B14: Regla de la consigna: no vale escribir 'mayor crecimiento'. Cada cifra alternativa sale del Motor y de los parámetros de 'Supuestos'; si un parámetro se discute, cámbielo y el presupuesto se recalcula.

Sheet Matriz_Instrumentos
B2: Segunda misión: cuatro contrafactuales (fiscal, monetario, cambiario, tributario) + social
B3: Distinguir lo que exige el acuerdo de lo que proponemos. Las cifras de costo se vinculan al Motor (E1–E5, año 2027).
B5: Área | C5: Exige el acuerdo FMI | D5: Pregunta contrafactual | E5: ¿Qué instrumento cambia? | F5: ¿Cómo funciona? | G5: ¿Quién gana? | H5: ¿Quién pierde? | I5: ¿Cuánto cuesta? (2027) | J5: ¿Cómo se financia? | K5: ¿Qué riesgo podría hacerla fracasar?
B6: Fiscal | C6: Consolidación anticipada: déficit primario −6,5% (2026) → −3,0% (2027) → +0,6% (2029); recorte de inversión pública 1 pp en 2026. | D6: ¿Reducir el déficit con otra velocidad protegiendo la inversión pública productiva? | E6: Senda de inversión pública: +1,0 pp PIB en 2027 sobre la senda FMI (E1). | F6: Proyectos con evaluación costo-beneficio (PIMA), contenido local y efecto oferta; multiplicador 0,7 vs 0,4 del gasto corriente. | G6: Construcción, proveedores locales, regiones con proyectos, empleo formal. | H6: Tenedores de deuda (más riesgo), sectores desplazados por el financiamiento interno. | I6: ="Déficit primario +"&TEXT(-Motor!E104,"0.00")&" pp PIB" -> Déficit primario +0.89 pp PIB | J6: CAF/BID préstamos de proyecto (US$ 500 mn 2027) + mercado interno (tope 1% PIB). Cero BCB. | K6: Credibilidad: si el desvío supera 0,5 pp sube la prima de riesgo; ejecución lenta; meta 2026 incumplida si se adelanta al 4º trimestre.
B7: Monetaria | C7: Base monetaria como ancla nominal con metas trimestrales; cero financiamiento al Estado; eliminar topes de tasas y cuotas de crédito (jun-2027). | D7: ¿Estabilizar precios sin restringir excesivamente el crédito? | E7: Encaje legal diferenciado para cartera productiva + fondos de garantía; base monetaria +1,5 pp en 2027 (E2). | F7: Libera liquidez hacia PyMEs y agro sin bajar la tasa de política; crédito +4 pp; elasticidad del PIB 0,12. | G7: PyMEs, productores, bancos con cartera productiva. | H7: Ahorristas (tasas reales menores); credibilidad del ancla si la expansión se desborda. | I7: ="Inflación +"&TEXT(Motor!E191,"0.00")&" pp; RIN "&TEXT(Motor!E201,"#,##0")&" US$ mn" -> Inflación +1.31 pp; RIN -196 US$ mn | J7: Neutral fiscalmente; costo cuasi-fiscal menor del BCB. | K7: Traspaso a precios y a dólar si la demanda de dinero no se recupera; selección adversa de cartera dirigida.
B8: Cambiaria | C8: Tipo de cambio flexible determinado por el mercado; intervención solo ante condiciones desordenadas; acumulación de reservas. | D8: ¿Una banda explícita administraría mejor la volatilidad? | E8: Banda deslizante ±7,5% con intervención en los bordes (E3). Alternativa E6: flotación administrada con regla de subasta. | F8: Ancla expectativas, reduce depreciación (−4 pp en 2027) y el traspaso (0,35) a precios. | G8: Importadores, deudores en dólares, hogares (menos inflación). | H8: Reservas: se venden divisas; exportadores (tipo de cambio menos competitivo). | I8: ="Reservas: "&TEXT(Motor!E273,"#,##0")&" US$ mn" -> Reservas: -478 US$ mn | J8: Con reservas propias; requiere colchón FLAR (US$ 700 mn) y regla de salida. | K8: Ataque especulativo si las RIN son bajas (≈1 mes de importaciones): la banda puede consumir reservas y romperse (ver shock de confianza).
B9: Tributaria | C9: Movilizar ≥1% PIB desde 2028 (estrategia, SB mar-2027); no nuevas exenciones sin compensación. Medidas 2025–26 restan 0,9% PIB. | D9: ¿Qué combinación de bases, progresividad, simplificación y menor evasión recaudaría más con menor daño productivo? | E9: Adelantar a 2027: anti-evasión IVA (facturación electrónica), renta personal y patrimonio, revisión de exenciones (E4). | F9: Recaudación potencial 1,2 pp en 2027 con realización 60–85%; multiplicadores bajos (0,10–0,30). | G9: Estado, hogares pobres (Gini −), contribuyentes cumplidos (competencia leal). | H9: Evasores, deciles altos, sectores con exenciones. | I9: ="Recaudación realizada +"&TEXT(Motor!E310,"0.00")&" pp PIB" -> Recaudación realizada +0.87 pp PIB | J9: Se autofinancia; reduce necesidad de deuda. | K9: Rechazo legislativo (freno legislativo), resistencia de gremios, capacidad del SIN.
B10: Social / subsidio | C10: Eliminar subsidio a combustibles a inicios de 2027 (mecanismo automático DS 5652); asistencia social ≥ Bs 9.300 mn (meta indicativa). | D10: ¿Menor costo social del ajuste? | E10: Diésel productivo focalizado transitorio (0,8 pp 2027) + asistencia +0,4 pp (E5). | F10: Amortigua inflación de transporte/alimentos; transferencias con multiplicador 0,6 y efecto directo en pobreza. | G10: Transportistas, agro, hogares pobres. | H10: Contribuyentes (costo fiscal), reservas (contrabando 30% del subsidio). | I10: ="Gasto +"&TEXT(Motor!E381,"0.00")&" pp PIB" -> Gasto +0.80 pp PIB | J10: Recorte de gasto corriente (−0,4 pp) y Banco Mundial (US$ 200 mn). | K10: Captura del subsidio por contrabando; postergar la reforma reabre el déficit; shock petrolero eleva el costo.

Sheet Diagnostico
B2: Primera misión: auditar el diagnóstico del FMI
B3: Regla: cada crítica identifica un supuesto, presenta evidencia y explica cómo cambiaría la política recomendada.
B5: Pregunta | C5: Lo que dice el FMI (evidencia del informe) | D5: Supuesto discutible / hipótesis alternativa | E5: Evidencia que permitiría contrastarla
B6: ¿Naturaleza de la crisis? | C6: Crisis fiscal y de balanza de pagos 2024–25 causada por déficits financiados por el BCB (6,8% PIB en 2025), paridad sobrevaluada e intervención estatal distorsionadora (párr. 1, 9). | D6: Componente productivo/estructural subestimado: caída de producción de gas (−20% en 2026) y agotamiento del modelo extractivo explican la pérdida de divisas tanto como el déficit. | E6: Descomposición de la caída de exportaciones (precio vs volumen de gas); reservas probadas; balanza energética 2014–2026.
B7: ¿Causas vs consecuencias? | C7: Déficit → monetización → brecha cambiaria → inflación y pérdida de reservas. | D7: Parte de la inflación 2025–26 responde a costos (combustibles +86%/+160%, bloqueos, depreciación) y no solo a exceso de dinero: la inflación cayó de 20% a 5% (ago-2026) con base monetaria −9%. | E7: Inflación subyacente vs alimentos/transporte; correlación base monetaria–IPC con rezagos; precios relativos post-dic-2025.
B8: ¿Supuestos del programa? | C8: Contracción −3,0% (2026) y −1,5% (2027); inflación de un dígito en 2028; financiamiento IFI de US$ 4.000 mn; respuesta de inversión privada a reformas. | D8: Multiplicadores fiscales bajos implícitos: un recorte de inversión de 1 pp en 2026 tiene costo de crecimiento y de potencial mayor al asumido; supuesto optimista de catalización privada. | E8: Ejecución de inversión pública vs PIB trimestral; IED neta (negativa en toda la proyección, Tabla 1); encuestas de inversión.
B9: ¿Riesgos que reconoce? | C9: Términos de intercambio (petróleo), malestar social, capacidad institucional limitada, fragmentación política y demoras del Congreso, datos débiles (párr. 33). | D9: El riesgo social está mitigado solo con asistencia mínima (0,6% PIB): con inflación de transporte y salarios públicos indexados al 30–50% de la inflación, la pérdida de ingreso real es grande. | E9: Evolución del salario real público y privado; pobreza trimestral (EH); número de conflictos/bloqueos.
B10: ¿Qué puede faltar? | C10: Énfasis en consolidación por el gasto (salarios −1,3 pp, bienes −1,3 pp, subsidios −6,2 pp) y movilización de ingresos recién desde 2028. | D10: Falta una estrategia productiva y tributaria progresiva temprana; la secuencia carga el ajuste en hogares y obra pública antes que en la base tributaria (exenciones 2025–26 cuestan 0,9% PIB). | E10: Gasto tributario por sector; brecha de IVA; incidencia distributiva del ajuste (microsimulación BM).

Sheet Objeciones_FMI
B2: Cuarta misión: la misión del FMI objeta
B3: Respuestas para el escenario E6, con cifras vinculadas al Motor y a Shocks.
B5: Pregunta difícil | C5: Respuesta del equipo | D5: Dato del modelo
B6: ¿Cómo financiarán un déficit mayor sin nuevo crédito del BCB? | C6: Fuentes identificadas: CAF/BID adicional (US$ 300 mn/año 2027–28) + colocación interna con tope de 1% PIB; la brecha residual se fuerza a cero (criterio continuo). Además el déficit no aumenta en neto: la reforma tributaria y el recorte corriente compensan la inversión. | D6: ="Crédito BCB E6 2026–29: Bs "&TEXT(Evaluacion!I17,"#,##0")&" mn" -> Crédito BCB E6 2026–29: Bs 0 mn
B7: ¿Qué harán si el petróleo sube 25%? | C7: No volver a congelar precios: el mecanismo automático traslada el alza (≈2 pp de inflación), con bono focalizado transitorio a transporte/agro. En 2026 (precios congelados) el costo es fiscal y de reservas. | D7: ="Importación extra de combustibles 2027: US$ "&TEXT(Shocks!C16*Datos_FMI!$G$26,"#,##0")&" mn" -> Importación extra de combustibles 2027: US$ 804 mn
B8: ¿Cómo impedirán que una banda cambiaria consuma reservas? | C8: E6 no adopta banda rígida: flotación administrada con subastas preanunciadas y tope de ventas (US$ 150 mn en 2027). Bajo banda (E3) una crisis de confianza consume 80% de la demanda adicional de dólares; con flotación, 20%. | D8: ="Pérdida de RIN E3 2026–29 vs FMI: US$ "&TEXT(Motor!G274,"#,##0")&" mn" -> Pérdida de RIN E3 2026–29 vs FMI: US$ -1,106 mn
B9: ¿Cuánto recaudarán realmente las reformas y en qué plazo? | C9: Se aplica tasa de realización: anti-evasión 70%, progresividad 60%, exenciones 85%. 2027: recaudación realizada menor al potencial; madura en 2028–29. | D9: ="Recaudación realizada E6 2027: "&TEXT(Motor!E454,"0.00")&" pp PIB; 2029: "&TEXT(Motor!G454,"0.00")&" pp" -> Recaudación realizada E6 2027: 0.63 pp PIB; 2029: 1.14 pp
B10: ¿Cómo evitarán que la política monetaria más expansiva aumente la inflación? | C10: El crédito productivo opera por encaje diferenciado (neutral en base monetaria); la base solo crece +0,5 pp sobre el programa en 2027–28 y se respeta el techo de dic-2026. Regla de reversión si la inflación supera la senda en 1 pp. | D10: ="Δ inflación E6 2027: "&TEXT(Motor!E479,"0.00")&" pp" -> Δ inflación E6 2027: 0.03 pp
B11: ¿Qué harán si el Congreso rechaza las reformas? | C11: Plan B: medidas administrativas sin ley (facturación, fiscalización, revisión de exenciones por decreto), reprogramar inversión no prioritaria y usar depósitos del SPNF en el BCB; meta de saldo primario se protege antes que la inversión. | D11: Ver hoja Shocks: 'Freno legislativo'

Sheet Negociacion
B2: Sexta misión: negociar un acuerdo alternativo
B3: No basta pedir más tiempo o dinero: metas verificables, calendario y seguimiento.
B5: Condicionalidad | C5: Programa FMI | D5: Propuesta alternativa (verificable) | E5: Calendario | F5: Seguimiento / indicador
B6: Saldo primario | C6: Piso −Bs 33.000 mn (dic-2026); −3,0% PIB en 2027. | D6: Mantener piso 2026. En 2027 piso de saldo primario 'excluyendo inversión productiva evaluada por PIMA' con tope de 0,6 pp PIB, compensado por recaudación adicional comprometida. | E6: Trimestral desde mar-2027 | F6: Saldo primario ajustado; cartera PIMA publicada
B7: Movilización de ingresos | C7: Estrategia (SB mar-2027); ≥1% PIB desde 2028. | D7: Nuevo SB: ley de renta personal/patrimonio presentada en dic-2026 y decreto de revisión de exenciones en mar-2027; meta indicativa de recaudación 2027 (+0,8 pp PIB). | E7: Dic-2026 / mar-2027 | F7: Recaudación mensual SIN/Aduana
B8: Subsidio a combustibles | C8: Eliminación a inicios de 2027 por mecanismo automático. | D8: Mecanismo automático para gasolina y diésel general; diésel productivo focalizado (registro) con tope 0,2 pp PIB y eliminación en dic-2027. | E8: Ene–dic 2027 | F8: Costo publicado mensualmente (Recuadro 1)
B9: Asistencia social | C9: Piso Bs 9.300 mn (meta indicativa). | D9: Piso más alto en 2027 (+0,25 pp PIB) ligado al registro social unificado. | E9: SB mar-2027 | F9: Gasto ejecutado y cobertura del quintil 1
B10: Política monetaria y crédito | C10: Techo de base monetaria; eliminar topes de tasas y cuotas (jun-2027). | D10: Aceptar techo y eliminación de topes; sustituir cuotas por encaje diferenciado transparente y fondos de garantía con cláusula de revisión. | E10: Jun-2027 | F10: Crédito productivo, mora, base monetaria
B11: Régimen cambiario | C11: Flotación; intervención solo ante desorden; marco FXI (SB dic-2026). | D11: Flotación administrada con reglas: subastas preanunciadas, tope anual de ventas netas (US$ 150 mn) y conservación del piso de RIN. | E11: Dic-2026 | F11: Ventas BCB publicadas; RIN programa
B12: Reservas | C12: Piso de variación de RIN (+US$ 2.400 mn en 2026). | D12: Se mantiene; ajustador simétrico por desembolsos IFI demorados (para no castigar retrasos legislativos). | E12: Trimestral | F12: RIN programa (MTE)
B14: Pregunta final (individual, ≤300 palabras): ¿Qué medida conservar, modificar y sustituir? ¿Qué evidencia demostraría que la propuesta estaba equivocada? Sugerencia: si con E6 la inflación 2027 supera la senda FMI en más de 1 pp, o la recaudación realizada 2027 queda bajo 0,5 pp PIB, o la prima de riesgo sube pese a cumplir metas, la hipótesis queda refutada.

Sheet Listas
K1: índices
B2: Base FMI | C2: Programa del EFF tal como fue aprobado: consolidación fiscal anticipada (déficit primario −6,5% → +0,6% del PIB), eliminación del subsidio a combustibles a inicios de 2027, flotación con intervención solo ante condiciones desordenadas, metas de base monetaria y cero financiamiento del BCB. | E2: Ninguno | G2: 2026 | I2: Sí | K2: =MATCH(sel_scen,Listas!$B$2:$B$8,0) -> 7
B3: E1 Fiscal gradual | C3: Misma meta de deuda pero con senda más lenta: se protege y amplía la inversión pública productiva (filtrada por PIMA), financiada con préstamos de proyecto de CAF/BID y mercado interno. Pregunta: ¿reducir el déficit con otra velocidad protegiendo la inversión? | E3: Shock petrolero (+25%) | G3: 2027 | I3: No | K3: =MATCH(sel_shock,Listas!$E$2:$E$7,0)-1 -> 0
B4: E2 Monetaria-crédito | C4: Se mantiene la meta de base monetaria 2026; desde 2027 expansión moderada y crédito productivo dirigido mediante encaje diferenciado y fondos de garantía (sin topes de tasas). Pregunta: ¿estabilizar precios sin restringir en exceso el crédito? | E4: Crisis de confianza | G4: 2028
B5: E3 Banda cambiaria | C5: Banda deslizante explícita (±7,5%) con intervención en los bordes para suavizar la depreciación y el traspaso a precios. Pregunta: ¿una banda administra mejor la volatilidad? Costo: reservas. | E5: Bloqueos (3 semanas)
B6: E4 Tributaria progresiva | C6: Adelanta la movilización de ingresos a 2027: lucha contra evasión (IVA, facturación), progresividad (renta personal, patrimonio, rentas financieras) y revisión de exenciones 2025–26. Pregunta: ¿qué combinación recauda más con menor daño productivo? | E6: Crisis bancaria
B7: E5 Protección social | C7: Desmonte gradual del subsidio (diésel productivo focalizado en 2027–28) y mayor asistencia social, compensados con recorte de gasto corriente y apoyo del Banco Mundial. Pregunta: ¿menor costo social del ajuste? | E7: Freno legislativo
B8: E6 Alternativo integrado | C8: Combinación eficiente: 2026 intacto para cumplir metas; desde 2027 inversión productiva + reforma tributaria progresiva/antievasión + recorte de gasto corriente y reestructuración de EP + crédito productivo neutral en base monetaria + flotación administrada con reglas + red social reforzada.
